{
  "results": {
    "dockerfile": {
      "exist": true,
      "count": 1,
      "rootCount": 1,
      "subFolderCount": 0,
      "filepaths": [
        "lucid-dynamodb.git/Dockerfile"
      ]
    },
    "composefile": {
      "exist": false,
      "count": 0,
      "rootCount": 0,
      "subFolderCount": 0,
      "filepaths": []
    },
    "devcontainer": {
      "exist": false,
      "count": 0,
      "rootCount": 0,
      "subFolderCount": 0,
      "filepaths": []
    },
    "kustomize": {
      "exist": false,
      "count": 0,
      "rootCount": 0,
      "subFolderCount": 0,
      "filepaths": []
    },
    "helm": {
      "exist": true,
      "count": 1,
      "rootCount": 0,
      "subFolderCount": 1,
      "filepaths": [
        "lucid-dynamodb.git/helm/Chart.yaml"
      ]
    },
    "k8s": {
      "exist": true,
      "count": 2,
      "rootCount": 0,
      "subFolderCount": 2,
      "filepaths": [
        "lucid-dynamodb.git/helm/templates/lucid-docs/deployment.yaml",
        "lucid-dynamodb.git/helm/templates/lucid-docs/service.yaml"
      ]
    },
    "backstage": {
      "exist": false,
      "count": 0,
      "rootCount": 0,
      "subFolderCount": 0,
      "filepaths": []
    },
    "terraform": {
      "exist": false,
      "count": 0,
      "rootCount": 0,
      "subFolderCount": 0,
      "filepaths": []
    }
  },
  "info": {
    "id": 65635235,
    "name": "lucid-dynamodb",
    "full_name": "dineshsonachalam/lucid-dynamodb",
    "owner": {
      "login": "dineshsonachalam",
      "html_url": "https://github.com/dineshsonachalam",
      "type": "User"
    },
    "html_url": "https://github.com/dineshsonachalam/lucid-dynamodb",
    "description": "🗄️ A simple Python wrapper to AWS Dynamodb.",
    "url": "https://api.github.com/repos/dineshsonachalam/lucid-dynamodb",
    "clone_url": "https://github.com/dineshsonachalam/lucid-dynamodb.git",
    "homepage": "https://lucid-dynamodb.dineshsonachalam.com",
    "size": 835,
    "stargazers_count": 107,
    "watchers_count": 107,
    "language": "Python"
  }
}