{
  "results": {
    "dockerfile": {
      "exist": true,
      "count": 1,
      "rootCount": 1,
      "subFolderCount": 0,
      "filepaths": [
        "jd-cli.git/Dockerfile"
      ]
    },
    "composefile": {
      "exist": false,
      "count": 0,
      "rootCount": 0,
      "subFolderCount": 0,
      "filepaths": []
    },
    "devcontainer": {
      "exist": false,
      "count": 0,
      "rootCount": 0,
      "subFolderCount": 0,
      "filepaths": []
    },
    "kustomize": {
      "exist": false,
      "count": 0,
      "rootCount": 0,
      "subFolderCount": 0,
      "filepaths": []
    },
    "helm": {
      "exist": false,
      "count": 0,
      "rootCount": 0,
      "subFolderCount": 0,
      "filepaths": []
    },
    "k8s": {
      "exist": false,
      "count": 0,
      "rootCount": 0,
      "subFolderCount": 0,
      "filepaths": []
    },
    "backstage": {
      "exist": false,
      "count": 0,
      "rootCount": 0,
      "subFolderCount": 0,
      "filepaths": []
    },
    "terraform": {
      "exist": false,
      "count": 0,
      "rootCount": 0,
      "subFolderCount": 0,
      "filepaths": []
    }
  },
  "info": {
    "id": 12640720,
    "name": "jd-cli",
    "full_name": "intoolswetrust/jd-cli",
    "owner": {
      "login": "intoolswetrust",
      "html_url": "https://github.com/intoolswetrust",
      "type": "Organization"
    },
    "html_url": "https://github.com/intoolswetrust/jd-cli",
    "description": "Command line Java Decompiler",
    "url": "https://api.github.com/repos/intoolswetrust/jd-cli",
    "clone_url": "https://github.com/intoolswetrust/jd-cli.git",
    "homepage": "",
    "size": 298,
    "stargazers_count": 471,
    "watchers_count": 471,
    "language": "Java"
  }
}