{
  "results": {
    "dockerfile": {
      "exist": true,
      "count": 2,
      "rootCount": 2,
      "subFolderCount": 0,
      "filepaths": [
        "swarm-exec.git/Dockerfile",
        "swarm-exec.git/Dockerfile.build"
      ]
    },
    "composefile": {
      "exist": false,
      "count": 0,
      "rootCount": 0,
      "subFolderCount": 0,
      "filepaths": []
    },
    "devcontainer": {
      "exist": false,
      "count": 0,
      "rootCount": 0,
      "subFolderCount": 0,
      "filepaths": []
    },
    "kustomize": {
      "exist": false,
      "count": 0,
      "rootCount": 0,
      "subFolderCount": 0,
      "filepaths": []
    },
    "helm": {
      "exist": false,
      "count": 0,
      "rootCount": 0,
      "subFolderCount": 0,
      "filepaths": []
    },
    "k8s": {
      "exist": false,
      "count": 0,
      "rootCount": 0,
      "subFolderCount": 0,
      "filepaths": []
    },
    "backstage": {
      "exist": false,
      "count": 0,
      "rootCount": 0,
      "subFolderCount": 0,
      "filepaths": []
    },
    "terraform": {
      "exist": false,
      "count": 0,
      "rootCount": 0,
      "subFolderCount": 0,
      "filepaths": []
    }
  },
  "info": {
    "id": 75981956,
    "name": "swarm-exec",
    "full_name": "mavenugo/swarm-exec",
    "owner": {
      "login": "mavenugo",
      "html_url": "https://github.com/mavenugo",
      "type": "User"
    },
    "html_url": "https://github.com/mavenugo/swarm-exec",
    "description": "Swarm Executor : Execute any docker command across swarm cluster",
    "url": "https://api.github.com/repos/mavenugo/swarm-exec",
    "clone_url": "https://github.com/mavenugo/swarm-exec.git",
    "homepage": "",
    "size": 757,
    "stargazers_count": 77,
    "watchers_count": 77,
    "language": "Shell"
  }
}