{
  "results": {
    "dockerfile": {
      "exist": true,
      "count": 7,
      "rootCount": 7,
      "subFolderCount": 0,
      "filepaths": [
        "napi-rs.git/aarch64.Dockerfile",
        "napi-rs.git/alpine-zig.Dockerfile",
        "napi-rs.git/alpine.Dockerfile",
        "napi-rs.git/armhf.Dockerfile",
        "napi-rs.git/debian-aarch64.Dockerfile",
        "napi-rs.git/debian-zig.Dockerfile",
        "napi-rs.git/debian.Dockerfile"
      ]
    },
    "composefile": {
      "exist": false,
      "count": 0,
      "rootCount": 0,
      "subFolderCount": 0,
      "filepaths": []
    },
    "kustomize": {
      "exist": false,
      "count": 0,
      "rootCount": 0,
      "subFolderCount": 0,
      "filepaths": []
    },
    "helm": {
      "exist": false,
      "count": 0,
      "rootCount": 0,
      "subFolderCount": 0,
      "filepaths": []
    },
    "k8s": {
      "exist": false,
      "count": 0,
      "rootCount": 0,
      "subFolderCount": 0,
      "filepaths": []
    },
    "backstage": {
      "exist": false,
      "count": 0,
      "rootCount": 0,
      "subFolderCount": 0,
      "filepaths": []
    },
    "terraform": {
      "exist": false,
      "count": 0,
      "rootCount": 0,
      "subFolderCount": 0,
      "filepaths": []
    }
  },
  "info": {
    "id": 131389850,
    "name": "napi-rs",
    "full_name": "napi-rs/napi-rs",
    "owner": {
      "login": "napi-rs",
      "html_url": "https://github.com/napi-rs",
      "type": "Organization"
    },
    "html_url": "https://github.com/napi-rs/napi-rs",
    "description": "A framework for building compiled Node.js add-ons in Rust via Node-API",
    "url": "https://api.github.com/repos/napi-rs/napi-rs",
    "clone_url": "https://github.com/napi-rs/napi-rs.git",
    "homepage": "https://napi.rs",
    "size": 16876,
    "stargazers_count": 3084,
    "watchers_count": 3084,
    "language": "Rust"
  }
}