{
  "results": {
    "dockerfile": {
      "exist": false,
      "count": 0,
      "rootCount": 0,
      "subFolderCount": 0,
      "filepaths": []
    },
    "composefile": {
      "exist": false,
      "count": 0,
      "rootCount": 0,
      "subFolderCount": 0,
      "filepaths": []
    },
    "devcontainer": {
      "exist": false,
      "count": 0,
      "rootCount": 0,
      "subFolderCount": 0,
      "filepaths": []
    },
    "kustomize": {
      "exist": false,
      "count": 0,
      "rootCount": 0,
      "subFolderCount": 0,
      "filepaths": []
    },
    "helm": {
      "exist": false,
      "count": 0,
      "rootCount": 0,
      "subFolderCount": 0,
      "filepaths": []
    },
    "k8s": {
      "exist": false,
      "count": 0,
      "rootCount": 0,
      "subFolderCount": 0,
      "filepaths": []
    },
    "backstage": {
      "exist": false,
      "count": 0,
      "rootCount": 0,
      "subFolderCount": 0,
      "filepaths": []
    },
    "terraform": {
      "exist": false,
      "count": 0,
      "rootCount": 0,
      "subFolderCount": 0,
      "filepaths": []
    }
  },
  "info": {
    "id": 23844491,
    "name": "omniplay",
    "full_name": "endplay/omniplay",
    "owner": {
      "login": "endplay",
      "html_url": "https://github.com/endplay",
      "type": "Organization"
    },
    "html_url": "https://github.com/endplay/omniplay",
    "description": "Arnold source code",
    "url": "https://api.github.com/repos/endplay/omniplay",
    "clone_url": "https://github.com/endplay/omniplay.git",
    "homepage": null,
    "size": 150039,
    "stargazers_count": 43,
    "watchers_count": 43,
    "language": "C"
  }
}