{
  "results": {
    "dockerfile": {
      "exist": false,
      "count": 0,
      "rootCount": 0,
      "subFolderCount": 0,
      "filepaths": []
    },
    "composefile": {
      "exist": false,
      "count": 0,
      "rootCount": 0,
      "subFolderCount": 0,
      "filepaths": []
    },
    "devcontainer": {
      "exist": false,
      "count": 0,
      "rootCount": 0,
      "subFolderCount": 0,
      "filepaths": []
    },
    "kustomize": {
      "exist": false,
      "count": 0,
      "rootCount": 0,
      "subFolderCount": 0,
      "filepaths": []
    },
    "helm": {
      "exist": false,
      "count": 0,
      "rootCount": 0,
      "subFolderCount": 0,
      "filepaths": []
    },
    "k8s": {
      "exist": false,
      "count": 0,
      "rootCount": 0,
      "subFolderCount": 0,
      "filepaths": []
    },
    "backstage": {
      "exist": false,
      "count": 0,
      "rootCount": 0,
      "subFolderCount": 0,
      "filepaths": []
    },
    "terraform": {
      "exist": false,
      "count": 0,
      "rootCount": 0,
      "subFolderCount": 0,
      "filepaths": []
    }
  },
  "info": {
    "id": 103301797,
    "name": "terraform-aws-rds",
    "full_name": "terraform-aws-modules/terraform-aws-rds",
    "owner": {
      "login": "terraform-aws-modules",
      "html_url": "https://github.com/terraform-aws-modules",
      "type": "Organization"
    },
    "html_url": "https://github.com/terraform-aws-modules/terraform-aws-rds",
    "description": "Terraform module which creates RDS resources on AWS 🇺🇦",
    "url": "https://api.github.com/repos/terraform-aws-modules/terraform-aws-rds",
    "clone_url": "https://github.com/terraform-aws-modules/terraform-aws-rds.git",
    "homepage": "https://registry.terraform.io/modules/terraform-aws-modules/rds/aws",
    "size": 4300,
    "stargazers_count": 689,
    "watchers_count": 689,
    "language": "HCL"
  }
}