{
  "results": {
    "dockerfile": {
      "exist": true,
      "count": 1,
      "rootCount": 1,
      "subFolderCount": 0,
      "filepaths": [
        "Ubuntu-Desktop-noVNC-Heroku-VPS.git/Dockerfile"
      ]
    },
    "composefile": {
      "exist": false,
      "count": 0,
      "rootCount": 0,
      "subFolderCount": 0,
      "filepaths": []
    },
    "devcontainer": {
      "exist": false,
      "count": 0,
      "rootCount": 0,
      "subFolderCount": 0,
      "filepaths": []
    },
    "kustomize": {
      "exist": false,
      "count": 0,
      "rootCount": 0,
      "subFolderCount": 0,
      "filepaths": []
    },
    "helm": {
      "exist": false,
      "count": 0,
      "rootCount": 0,
      "subFolderCount": 0,
      "filepaths": []
    },
    "k8s": {
      "exist": false,
      "count": 0,
      "rootCount": 0,
      "subFolderCount": 0,
      "filepaths": []
    },
    "backstage": {
      "exist": false,
      "count": 0,
      "rootCount": 0,
      "subFolderCount": 0,
      "filepaths": []
    },
    "terraform": {
      "exist": false,
      "count": 0,
      "rootCount": 0,
      "subFolderCount": 0,
      "filepaths": []
    }
  },
  "info": {
    "id": 368798652,
    "name": "Ubuntu-Desktop-noVNC-Heroku-VPS",
    "full_name": "developeranaz/Ubuntu-Desktop-noVNC-Heroku-VPS",
    "owner": {
      "login": "developeranaz",
      "html_url": "https://github.com/developeranaz",
      "type": "User"
    },
    "html_url": "https://github.com/developeranaz/Ubuntu-Desktop-noVNC-Heroku-VPS",
    "description": "Ubuntu-Desktop-noVNC-Heroku-VPS serves docker VPS via heroku web and noVNC",
    "url": "https://api.github.com/repos/developeranaz/Ubuntu-Desktop-noVNC-Heroku-VPS",
    "clone_url": "https://github.com/developeranaz/Ubuntu-Desktop-noVNC-Heroku-VPS.git",
    "homepage": null,
    "size": 1395,
    "stargazers_count": 53,
    "watchers_count": 53,
    "language": "Dockerfile"
  }
}