{
  "results": {
    "dockerfile": {
      "exist": false,
      "count": 0,
      "rootCount": 0,
      "subFolderCount": 0,
      "filepaths": []
    },
    "composefile": {
      "exist": false,
      "count": 0,
      "rootCount": 0,
      "subFolderCount": 0,
      "filepaths": []
    }
  },
  "struct": {
    ".git": {
      "name": ".git",
      "path": "EFCore.Sharding.git/.git",
      "isDir": true,
      "isDockerfile": false,
      "isComposefile": false,
      "children": {
        "HEAD": {
          "name": "HEAD",
          "path": "EFCore.Sharding.git/.git/HEAD",
          "isDir": false,
          "isDockerfile": false,
          "isComposefile": false
        },
        "config": {
          "name": "config",
          "path": "EFCore.Sharding.git/.git/config",
          "isDir": false,
          "isDockerfile": false,
          "isComposefile": false
        },
        "description": {
          "name": "description",
          "path": "EFCore.Sharding.git/.git/description",
          "isDir": false,
          "isDockerfile": false,
          "isComposefile": false
        },
        "hooks": {
          "name": "hooks",
          "path": "EFCore.Sharding.git/.git/hooks",
          "isDir": true,
          "isDockerfile": false,
          "isComposefile": false,
          "children": {
            "applypatch-msg.sample": {
              "name": "applypatch-msg.sample",
              "path": "EFCore.Sharding.git/.git/hooks/applypatch-msg.sample",
              "isDir": false,
              "isDockerfile": false,
              "isComposefile": false
            },
            "commit-msg.sample": {
              "name": "commit-msg.sample",
              "path": "EFCore.Sharding.git/.git/hooks/commit-msg.sample",
              "isDir": false,
              "isDockerfile": false,
              "isComposefile": false
            },
            "fsmonitor-watchman.sample": {
              "name": "fsmonitor-watchman.sample",
              "path": "EFCore.Sharding.git/.git/hooks/fsmonitor-watchman.sample",
              "isDir": false,
              "isDockerfile": false,
              "isComposefile": false
            },
            "post-update.sample": {
              "name": "post-update.sample",
              "path": "EFCore.Sharding.git/.git/hooks/post-update.sample",
              "isDir": false,
              "isDockerfile": false,
              "isComposefile": false
            },
            "pre-applypatch.sample": {
              "name": "pre-applypatch.sample",
              "path": "EFCore.Sharding.git/.git/hooks/pre-applypatch.sample",
              "isDir": false,
              "isDockerfile": false,
              "isComposefile": false
            },
            "pre-commit.sample": {
              "name": "pre-commit.sample",
              "path": "EFCore.Sharding.git/.git/hooks/pre-commit.sample",
              "isDir": false,
              "isDockerfile": false,
              "isComposefile": false
            },
            "pre-merge-commit.sample": {
              "name": "pre-merge-commit.sample",
              "path": "EFCore.Sharding.git/.git/hooks/pre-merge-commit.sample",
              "isDir": false,
              "isDockerfile": false,
              "isComposefile": false
            },
            "pre-push.sample": {
              "name": "pre-push.sample",
              "path": "EFCore.Sharding.git/.git/hooks/pre-push.sample",
              "isDir": false,
              "isDockerfile": false,
              "isComposefile": false
            },
            "pre-rebase.sample": {
              "name": "pre-rebase.sample",
              "path": "EFCore.Sharding.git/.git/hooks/pre-rebase.sample",
              "isDir": false,
              "isDockerfile": false,
              "isComposefile": false
            },
            "pre-receive.sample": {
              "name": "pre-receive.sample",
              "path": "EFCore.Sharding.git/.git/hooks/pre-receive.sample",
              "isDir": false,
              "isDockerfile": false,
              "isComposefile": false
            },
            "prepare-commit-msg.sample": {
              "name": "prepare-commit-msg.sample",
              "path": "EFCore.Sharding.git/.git/hooks/prepare-commit-msg.sample",
              "isDir": false,
              "isDockerfile": false,
              "isComposefile": false
            },
            "push-to-checkout.sample": {
              "name": "push-to-checkout.sample",
              "path": "EFCore.Sharding.git/.git/hooks/push-to-checkout.sample",
              "isDir": false,
              "isDockerfile": false,
              "isComposefile": false
            },
            "update.sample": {
              "name": "update.sample",
              "path": "EFCore.Sharding.git/.git/hooks/update.sample",
              "isDir": false,
              "isDockerfile": false,
              "isComposefile": false
            }
          }
        },
        "index": {
          "name": "index",
          "path": "EFCore.Sharding.git/.git/index",
          "isDir": false,
          "isDockerfile": false,
          "isComposefile": false
        },
        "info": {
          "name": "info",
          "path": "EFCore.Sharding.git/.git/info",
          "isDir": true,
          "isDockerfile": false,
          "isComposefile": false,
          "children": {
            "exclude": {
              "name": "exclude",
              "path": "EFCore.Sharding.git/.git/info/exclude",
              "isDir": false,
              "isDockerfile": false,
              "isComposefile": false
            }
          }
        },
        "logs": {
          "name": "logs",
          "path": "EFCore.Sharding.git/.git/logs",
          "isDir": true,
          "isDockerfile": false,
          "isComposefile": false,
          "children": {
            "HEAD": {
              "name": "HEAD",
              "path": "EFCore.Sharding.git/.git/logs/HEAD",
              "isDir": false,
              "isDockerfile": false,
              "isComposefile": false
            },
            "refs": {
              "name": "refs",
              "path": "EFCore.Sharding.git/.git/logs/refs",
              "isDir": true,
              "isDockerfile": false,
              "isComposefile": false,
              "children": {
                "heads": {
                  "name": "heads",
                  "path": "EFCore.Sharding.git/.git/logs/refs/heads",
                  "isDir": true,
                  "isDockerfile": false,
                  "isComposefile": false,
                  "children": {
                    "master": {
                      "name": "master",
                      "path": "EFCore.Sharding.git/.git/logs/refs/heads/master",
                      "isDir": false,
                      "isDockerfile": false,
                      "isComposefile": false
                    }
                  }
                },
                "remotes": {
                  "name": "remotes",
                  "path": "EFCore.Sharding.git/.git/logs/refs/remotes",
                  "isDir": true,
                  "isDockerfile": false,
                  "isComposefile": false,
                  "children": {
                    "origin": {
                      "name": "origin",
                      "path": "EFCore.Sharding.git/.git/logs/refs/remotes/origin",
                      "isDir": true,
                      "isDockerfile": false,
                      "isComposefile": false,
                      "children": {
                        "HEAD": {
                          "name": "HEAD",
                          "path": "EFCore.Sharding.git/.git/logs/refs/remotes/origin/HEAD",
                          "isDir": false,
                          "isDockerfile": false,
                          "isComposefile": false
                        }
                      }
                    }
                  }
                }
              }
            }
          }
        },
        "objects": {
          "name": "objects",
          "path": "EFCore.Sharding.git/.git/objects",
          "isDir": true,
          "isDockerfile": false,
          "isComposefile": false,
          "children": {
            "info": {
              "name": "info",
              "path": "EFCore.Sharding.git/.git/objects/info",
              "isDir": true,
              "isDockerfile": false,
              "isComposefile": false,
              "children": {}
            },
            "pack": {
              "name": "pack",
              "path": "EFCore.Sharding.git/.git/objects/pack",
              "isDir": true,
              "isDockerfile": false,
              "isComposefile": false,
              "children": {
                "pack-119d4d6e7218186dae34e43df72efe6ca506c2fe.idx": {
                  "name": "pack-119d4d6e7218186dae34e43df72efe6ca506c2fe.idx",
                  "path": "EFCore.Sharding.git/.git/objects/pack/pack-119d4d6e7218186dae34e43df72efe6ca506c2fe.idx",
                  "isDir": false,
                  "isDockerfile": false,
                  "isComposefile": false
                },
                "pack-119d4d6e7218186dae34e43df72efe6ca506c2fe.pack": {
                  "name": "pack-119d4d6e7218186dae34e43df72efe6ca506c2fe.pack",
                  "path": "EFCore.Sharding.git/.git/objects/pack/pack-119d4d6e7218186dae34e43df72efe6ca506c2fe.pack",
                  "isDir": false,
                  "isDockerfile": false,
                  "isComposefile": false
                }
              }
            }
          }
        },
        "packed-refs": {
          "name": "packed-refs",
          "path": "EFCore.Sharding.git/.git/packed-refs",
          "isDir": false,
          "isDockerfile": false,
          "isComposefile": false
        },
        "refs": {
          "name": "refs",
          "path": "EFCore.Sharding.git/.git/refs",
          "isDir": true,
          "isDockerfile": false,
          "isComposefile": false,
          "children": {
            "heads": {
              "name": "heads",
              "path": "EFCore.Sharding.git/.git/refs/heads",
              "isDir": true,
              "isDockerfile": false,
              "isComposefile": false,
              "children": {
                "master": {
                  "name": "master",
                  "path": "EFCore.Sharding.git/.git/refs/heads/master",
                  "isDir": false,
                  "isDockerfile": false,
                  "isComposefile": false
                }
              }
            },
            "remotes": {
              "name": "remotes",
              "path": "EFCore.Sharding.git/.git/refs/remotes",
              "isDir": true,
              "isDockerfile": false,
              "isComposefile": false,
              "children": {
                "origin": {
                  "name": "origin",
                  "path": "EFCore.Sharding.git/.git/refs/remotes/origin",
                  "isDir": true,
                  "isDockerfile": false,
                  "isComposefile": false,
                  "children": {
                    "HEAD": {
                      "name": "HEAD",
                      "path": "EFCore.Sharding.git/.git/refs/remotes/origin/HEAD",
                      "isDir": false,
                      "isDockerfile": false,
                      "isComposefile": false
                    }
                  }
                }
              }
            },
            "tags": {
              "name": "tags",
              "path": "EFCore.Sharding.git/.git/refs/tags",
              "isDir": true,
              "isDockerfile": false,
              "isComposefile": false,
              "children": {
                "6.0.7": {
                  "name": "6.0.7",
                  "path": "EFCore.Sharding.git/.git/refs/tags/6.0.7",
                  "isDir": false,
                  "isDockerfile": false,
                  "isComposefile": false
                }
              }
            }
          }
        },
        "shallow": {
          "name": "shallow",
          "path": "EFCore.Sharding.git/.git/shallow",
          "isDir": false,
          "isDockerfile": false,
          "isComposefile": false
        }
      }
    },
    ".gitattributes": {
      "name": ".gitattributes",
      "path": "EFCore.Sharding.git/.gitattributes",
      "isDir": false,
      "isDockerfile": false,
      "isComposefile": false
    },
    ".gitignore": {
      "name": ".gitignore",
      "path": "EFCore.Sharding.git/.gitignore",
      "isDir": false,
      "isDockerfile": false,
      "isComposefile": false
    },
    "Directory.Build.props": {
      "name": "Directory.Build.props",
      "path": "EFCore.Sharding.git/Directory.Build.props",
      "isDir": false,
      "isDockerfile": false,
      "isComposefile": false
    },
    "EFCore.Sharding.sln": {
      "name": "EFCore.Sharding.sln",
      "path": "EFCore.Sharding.git/EFCore.Sharding.sln",
      "isDir": false,
      "isDockerfile": false,
      "isComposefile": false
    },
    "LICENSE": {
      "name": "LICENSE",
      "path": "EFCore.Sharding.git/LICENSE",
      "isDir": false,
      "isDockerfile": false,
      "isComposefile": false
    },
    "README.md": {
      "name": "README.md",
      "path": "EFCore.Sharding.git/README.md",
      "isDir": false,
      "isDockerfile": false,
      "isComposefile": false
    },
    "clear.bat": {
      "name": "clear.bat",
      "path": "EFCore.Sharding.git/clear.bat",
      "isDir": false,
      "isDockerfile": false,
      "isComposefile": false
    },
    "examples": {
      "name": "examples",
      "path": "EFCore.Sharding.git/examples",
      "isDir": true,
      "isDockerfile": false,
      "isComposefile": false,
      "children": {
        "Demo.DateSharding": {
          "name": "Demo.DateSharding",
          "path": "EFCore.Sharding.git/examples/Demo.DateSharding",
          "isDir": true,
          "isDockerfile": false,
          "isComposefile": false,
          "children": {
            "Demo.DateSharding.csproj": {
              "name": "Demo.DateSharding.csproj",
              "path": "EFCore.Sharding.git/examples/Demo.DateSharding/Demo.DateSharding.csproj",
              "isDir": false,
              "isDockerfile": false,
              "isComposefile": false
            },
            "Program.cs": {
              "name": "Program.cs",
              "path": "EFCore.Sharding.git/examples/Demo.DateSharding/Program.cs",
              "isDir": false,
              "isDockerfile": false,
              "isComposefile": false
            }
          }
        },
        "Demo.DbMigrator": {
          "name": "Demo.DbMigrator",
          "path": "EFCore.Sharding.git/examples/Demo.DbMigrator",
          "isDir": true,
          "isDockerfile": false,
          "isComposefile": false,
          "children": {
            "CustomContext.cs": {
              "name": "CustomContext.cs",
              "path": "EFCore.Sharding.git/examples/Demo.DbMigrator/CustomContext.cs",
              "isDir": false,
              "isDockerfile": false,
              "isComposefile": false
            },
            "Demo.DbMigrator.csproj": {
              "name": "Demo.DbMigrator.csproj",
              "path": "EFCore.Sharding.git/examples/Demo.DbMigrator/Demo.DbMigrator.csproj",
              "isDir": false,
              "isDockerfile": false,
              "isComposefile": false
            },
            "DesignTimeDbContextFactory.cs": {
              "name": "DesignTimeDbContextFactory.cs",
              "path": "EFCore.Sharding.git/examples/Demo.DbMigrator/DesignTimeDbContextFactory.cs",
              "isDir": false,
              "isDockerfile": false,
              "isComposefile": false
            },
            "Entities": {
              "name": "Entities",
              "path": "EFCore.Sharding.git/examples/Demo.DbMigrator/Entities",
              "isDir": true,
              "isDockerfile": false,
              "isComposefile": false,
              "children": {
                "AuditLog.cs": {
                  "name": "AuditLog.cs",
                  "path": "EFCore.Sharding.git/examples/Demo.DbMigrator/Entities/AuditLog.cs",
                  "isDir": false,
                  "isDockerfile": false,
                  "isComposefile": false
                },
                "Order.cs": {
                  "name": "Order.cs",
                  "path": "EFCore.Sharding.git/examples/Demo.DbMigrator/Entities/Order.cs",
                  "isDir": false,
                  "isDockerfile": false,
                  "isComposefile": false
                },
                "OrderItem.cs": {
                  "name": "OrderItem.cs",
                  "path": "EFCore.Sharding.git/examples/Demo.DbMigrator/Entities/OrderItem.cs",
                  "isDir": false,
                  "isDockerfile": false,
                  "isComposefile": false
                },
                "OrderTypes.cs": {
                  "name": "OrderTypes.cs",
                  "path": "EFCore.Sharding.git/examples/Demo.DbMigrator/Entities/OrderTypes.cs",
                  "isDir": false,
                  "isDockerfile": false,
                  "isComposefile": false
                }
              }
            },
            "EntityTypeConfigurations": {
              "name": "EntityTypeConfigurations",
              "path": "EFCore.Sharding.git/examples/Demo.DbMigrator/EntityTypeConfigurations",
              "isDir": true,
              "isDockerfile": false,
              "isComposefile": false,
              "children": {
                "AuditLog_Configuration.cs": {
                  "name": "AuditLog_Configuration.cs",
                  "path": "EFCore.Sharding.git/examples/Demo.DbMigrator/EntityTypeConfigurations/AuditLog_Configuration.cs",
                  "isDir": false,
                  "isDockerfile": false,
                  "isComposefile": false
                },
                "Order_Configuration.cs": {
                  "name": "Order_Configuration.cs",
                  "path": "EFCore.Sharding.git/examples/Demo.DbMigrator/EntityTypeConfigurations/Order_Configuration.cs",
                  "isDir": false,
                  "isDockerfile": false,
                  "isComposefile": false
                }
              }
            },
            "Migrations": {
              "name": "Migrations",
              "path": "EFCore.Sharding.git/examples/Demo.DbMigrator/Migrations",
              "isDir": true,
              "isDockerfile": false,
              "isComposefile": false,
              "children": {
                "20210321082807_InitialCreate.Designer.cs": {
                  "name": "20210321082807_InitialCreate.Designer.cs",
                  "path": "EFCore.Sharding.git/examples/Demo.DbMigrator/Migrations/20210321082807_InitialCreate.Designer.cs",
                  "isDir": false,
                  "isDockerfile": false,
                  "isComposefile": false
                },
                "20210321082807_InitialCreate.cs": {
                  "name": "20210321082807_InitialCreate.cs",
                  "path": "EFCore.Sharding.git/examples/Demo.DbMigrator/Migrations/20210321082807_InitialCreate.cs",
                  "isDir": false,
                  "isDockerfile": false,
                  "isComposefile": false
                },
                "CustomContextModelSnapshot.cs": {
                  "name": "CustomContextModelSnapshot.cs",
                  "path": "EFCore.Sharding.git/examples/Demo.DbMigrator/Migrations/CustomContextModelSnapshot.cs",
                  "isDir": false,
                  "isDockerfile": false,
                  "isComposefile": false
                }
              }
            },
            "Program.cs": {
              "name": "Program.cs",
              "path": "EFCore.Sharding.git/examples/Demo.DbMigrator/Program.cs",
              "isDir": false,
              "isDockerfile": false,
              "isComposefile": false
            },
            "readme.md": {
              "name": "readme.md",
              "path": "EFCore.Sharding.git/examples/Demo.DbMigrator/readme.md",
              "isDir": false,
              "isDockerfile": false,
              "isComposefile": false
            }
          }
        },
        "Demo.HelloWorld": {
          "name": "Demo.HelloWorld",
          "path": "EFCore.Sharding.git/examples/Demo.HelloWorld",
          "isDir": true,
          "isDockerfile": false,
          "isComposefile": false,
          "children": {
            "Demo.HelloWorld.csproj": {
              "name": "Demo.HelloWorld.csproj",
              "path": "EFCore.Sharding.git/examples/Demo.HelloWorld/Demo.HelloWorld.csproj",
              "isDir": false,
              "isDockerfile": false,
              "isComposefile": false
            },
            "Program.cs": {
              "name": "Program.cs",
              "path": "EFCore.Sharding.git/examples/Demo.HelloWorld/Program.cs",
              "isDir": false,
              "isDockerfile": false,
              "isComposefile": false
            }
          }
        },
        "Demo.ModSharding": {
          "name": "Demo.ModSharding",
          "path": "EFCore.Sharding.git/examples/Demo.ModSharding",
          "isDir": true,
          "isDockerfile": false,
          "isComposefile": false,
          "children": {
            "Demo.ModSharding.csproj": {
              "name": "Demo.ModSharding.csproj",
              "path": "EFCore.Sharding.git/examples/Demo.ModSharding/Demo.ModSharding.csproj",
              "isDir": false,
              "isDockerfile": false,
              "isComposefile": false
            },
            "Program.cs": {
              "name": "Program.cs",
              "path": "EFCore.Sharding.git/examples/Demo.ModSharding/Program.cs",
              "isDir": false,
              "isDockerfile": false,
              "isComposefile": false
            }
          }
        },
        "Demo.Performance": {
          "name": "Demo.Performance",
          "path": "EFCore.Sharding.git/examples/Demo.Performance",
          "isDir": true,
          "isDockerfile": false,
          "isComposefile": false,
          "children": {
            "Demo.Performance.2x.csproj": {
              "name": "Demo.Performance.2x.csproj",
              "path": "EFCore.Sharding.git/examples/Demo.Performance/Demo.Performance.2x.csproj",
              "isDir": false,
              "isDockerfile": false,
              "isComposefile": false
            },
            "Demo.Performance.csproj": {
              "name": "Demo.Performance.csproj",
              "path": "EFCore.Sharding.git/examples/Demo.Performance/Demo.Performance.csproj",
              "isDir": false,
              "isDockerfile": false,
              "isComposefile": false
            },
            "Program.cs": {
              "name": "Program.cs",
              "path": "EFCore.Sharding.git/examples/Demo.Performance/Program.cs",
              "isDir": false,
              "isDockerfile": false,
              "isComposefile": false
            }
          }
        },
        "Demo.ReadWrite": {
          "name": "Demo.ReadWrite",
          "path": "EFCore.Sharding.git/examples/Demo.ReadWrite",
          "isDir": true,
          "isDockerfile": false,
          "isComposefile": false,
          "children": {
            "Demo.ReadWrite.csproj": {
              "name": "Demo.ReadWrite.csproj",
              "path": "EFCore.Sharding.git/examples/Demo.ReadWrite/Demo.ReadWrite.csproj",
              "isDir": false,
              "isDockerfile": false,
              "isComposefile": false
            },
            "Program.cs": {
              "name": "Program.cs",
              "path": "EFCore.Sharding.git/examples/Demo.ReadWrite/Program.cs",
              "isDir": false,
              "isDockerfile": false,
              "isComposefile": false
            }
          }
        }
      }
    },
    "gitversion.yml": {
      "name": "gitversion.yml",
      "path": "EFCore.Sharding.git/gitversion.yml",
      "isDir": false,
      "isDockerfile": false,
      "isComposefile": false
    },
    "global.json": {
      "name": "global.json",
      "path": "EFCore.Sharding.git/global.json",
      "isDir": false,
      "isDockerfile": false,
      "isComposefile": false
    },
    "src": {
      "name": "src",
      "path": "EFCore.Sharding.git/src",
      "isDir": true,
      "isDockerfile": false,
      "isComposefile": false,
      "children": {
        "EFCore.Sharding": {
          "name": "EFCore.Sharding",
          "path": "EFCore.Sharding.git/src/EFCore.Sharding",
          "isDir": true,
          "isDockerfile": false,
          "isComposefile": false,
          "children": {
            "AbstractProvider.cs": {
              "name": "AbstractProvider.cs",
              "path": "EFCore.Sharding.git/src/EFCore.Sharding/AbstractProvider.cs",
              "isDir": false,
              "isDockerfile": false,
              "isComposefile": false
            },
            "DbAccessor": {
              "name": "DbAccessor",
              "path": "EFCore.Sharding.git/src/EFCore.Sharding/DbAccessor",
              "isDir": true,
              "isDockerfile": false,
              "isComposefile": false,
              "children": {
                "DefaultBaseDbAccessor.cs": {
                  "name": "DefaultBaseDbAccessor.cs",
                  "path": "EFCore.Sharding.git/src/EFCore.Sharding/DbAccessor/DefaultBaseDbAccessor.cs",
                  "isDir": false,
                  "isDockerfile": false,
                  "isComposefile": false
                },
                "DefaultDbAccessor.cs": {
                  "name": "DefaultDbAccessor.cs",
                  "path": "EFCore.Sharding.git/src/EFCore.Sharding/DbAccessor/DefaultDbAccessor.cs",
                  "isDir": false,
                  "isDockerfile": false,
                  "isComposefile": false
                },
                "GenericDbAccessor.cs": {
                  "name": "GenericDbAccessor.cs",
                  "path": "EFCore.Sharding.git/src/EFCore.Sharding/DbAccessor/GenericDbAccessor.cs",
                  "isDir": false,
                  "isDockerfile": false,
                  "isComposefile": false
                },
                "LogicDeleteDbAccessor.cs": {
                  "name": "LogicDeleteDbAccessor.cs",
                  "path": "EFCore.Sharding.git/src/EFCore.Sharding/DbAccessor/LogicDeleteDbAccessor.cs",
                  "isDir": false,
                  "isDockerfile": false,
                  "isComposefile": false
                },
                "ReadWriteDbAccessor.cs": {
                  "name": "ReadWriteDbAccessor.cs",
                  "path": "EFCore.Sharding.git/src/EFCore.Sharding/DbAccessor/ReadWriteDbAccessor.cs",
                  "isDir": false,
                  "isDockerfile": false,
                  "isComposefile": false
                }
              }
            },
            "DbContext": {
              "name": "DbContext",
              "path": "EFCore.Sharding.git/src/EFCore.Sharding/DbContext",
              "isDir": true,
              "isDockerfile": false,
              "isComposefile": false,
              "children": {
                "DbContextParamters.cs": {
                  "name": "DbContextParamters.cs",
                  "path": "EFCore.Sharding.git/src/EFCore.Sharding/DbContext/DbContextParamters.cs",
                  "isDir": false,
                  "isDockerfile": false,
                  "isComposefile": false
                },
                "GenericDbContext.cs": {
                  "name": "GenericDbContext.cs",
                  "path": "EFCore.Sharding.git/src/EFCore.Sharding/DbContext/GenericDbContext.cs",
                  "isDir": false,
                  "isDockerfile": false,
                  "isComposefile": false
                },
                "GenericModelCacheKeyFactory.cs": {
                  "name": "GenericModelCacheKeyFactory.cs",
                  "path": "EFCore.Sharding.git/src/EFCore.Sharding/DbContext/GenericModelCacheKeyFactory.cs",
                  "isDir": false,
                  "isDockerfile": false,
                  "isComposefile": false
                }
              }
            },
            "DbFactory.cs": {
              "name": "DbFactory.cs",
              "path": "EFCore.Sharding.git/src/EFCore.Sharding/DbFactory.cs",
              "isDir": false,
              "isDockerfile": false,
              "isComposefile": false
            },
            "DependencyInjection": {
              "name": "DependencyInjection",
              "path": "EFCore.Sharding.git/src/EFCore.Sharding/DependencyInjection",
              "isDir": true,
              "isDockerfile": false,
              "isComposefile": false,
              "children": {
                "Cache.cs": {
                  "name": "Cache.cs",
                  "path": "EFCore.Sharding.git/src/EFCore.Sharding/DependencyInjection/Cache.cs",
                  "isDir": false,
                  "isDockerfile": false,
                  "isComposefile": false
                },
                "EFCoreShardingBootstrapper.cs": {
                  "name": "EFCoreShardingBootstrapper.cs",
                  "path": "EFCore.Sharding.git/src/EFCore.Sharding/DependencyInjection/EFCoreShardingBootstrapper.cs",
                  "isDir": false,
                  "isDockerfile": false,
                  "isComposefile": false
                },
                "EFCoreShardingExtensions.cs": {
                  "name": "EFCoreShardingExtensions.cs",
                  "path": "EFCore.Sharding.git/src/EFCore.Sharding/DependencyInjection/EFCoreShardingExtensions.cs",
                  "isDir": false,
                  "isDockerfile": false,
                  "isComposefile": false
                },
                "IShardingBuilder.cs": {
                  "name": "IShardingBuilder.cs",
                  "path": "EFCore.Sharding.git/src/EFCore.Sharding/DependencyInjection/IShardingBuilder.cs",
                  "isDir": false,
                  "isDockerfile": false,
                  "isComposefile": false
                },
                "IShardingConfig.cs": {
                  "name": "IShardingConfig.cs",
                  "path": "EFCore.Sharding.git/src/EFCore.Sharding/DependencyInjection/IShardingConfig.cs",
                  "isDir": false,
                  "isDockerfile": false,
                  "isComposefile": false
                },
                "ShardingConstant.cs": {
                  "name": "ShardingConstant.cs",
                  "path": "EFCore.Sharding.git/src/EFCore.Sharding/DependencyInjection/ShardingConstant.cs",
                  "isDir": false,
                  "isDockerfile": false,
                  "isComposefile": false
                },
                "ShardingContainer.cs": {
                  "name": "ShardingContainer.cs",
                  "path": "EFCore.Sharding.git/src/EFCore.Sharding/DependencyInjection/ShardingContainer.cs",
                  "isDir": false,
                  "isDockerfile": false,
                  "isComposefile": false
                }
              }
            },
            "Diagnostics": {
              "name": "Diagnostics",
              "path": "EFCore.Sharding.git/src/EFCore.Sharding/Diagnostics",
              "isDir": true,
              "isDockerfile": false,
              "isComposefile": false,
              "children": {
                "DiagnosticObserver.cs": {
                  "name": "DiagnosticObserver.cs",
                  "path": "EFCore.Sharding.git/src/EFCore.Sharding/Diagnostics/DiagnosticObserver.cs",
                  "isDir": false,
                  "isDockerfile": false,
                  "isComposefile": false
                },
                "KeyValueObserver.cs": {
                  "name": "KeyValueObserver.cs",
                  "path": "EFCore.Sharding.git/src/EFCore.Sharding/Diagnostics/KeyValueObserver.cs",
                  "isDir": false,
                  "isDockerfile": false,
                  "isComposefile": false
                }
              }
            },
            "EFCore.Sharding.csproj": {
              "name": "EFCore.Sharding.csproj",
              "path": "EFCore.Sharding.git/src/EFCore.Sharding/EFCore.Sharding.csproj",
              "isDir": false,
              "isDockerfile": false,
              "isComposefile": false
            },
            "IDbAccessor": {
              "name": "IDbAccessor",
              "path": "EFCore.Sharding.git/src/EFCore.Sharding/IDbAccessor",
              "isDir": true,
              "isDockerfile": false,
              "isComposefile": false,
              "children": {
                "IBaseDbAccessor.cs": {
                  "name": "IBaseDbAccessor.cs",
                  "path": "EFCore.Sharding.git/src/EFCore.Sharding/IDbAccessor/IBaseDbAccessor.cs",
                  "isDir": false,
                  "isDockerfile": false,
                  "isComposefile": false
                },
                "IDbAccessor.cs": {
                  "name": "IDbAccessor.cs",
                  "path": "EFCore.Sharding.git/src/EFCore.Sharding/IDbAccessor/IDbAccessor.cs",
                  "isDir": false,
                  "isDockerfile": false,
                  "isComposefile": false
                },
                "IShardingDbAccessor.cs": {
                  "name": "IShardingDbAccessor.cs",
                  "path": "EFCore.Sharding.git/src/EFCore.Sharding/IDbAccessor/IShardingDbAccessor.cs",
                  "isDir": false,
                  "isDockerfile": false,
                  "isComposefile": false
                }
              }
            },
            "IDbFactory.cs": {
              "name": "IDbFactory.cs",
              "path": "EFCore.Sharding.git/src/EFCore.Sharding/IDbFactory.cs",
              "isDir": false,
              "isDockerfile": false,
              "isComposefile": false
            },
            "Migrations": {
              "name": "Migrations",
              "path": "EFCore.Sharding.git/src/EFCore.Sharding/Migrations",
              "isDir": true,
              "isDockerfile": false,
              "isComposefile": false,
              "children": {
                "MigrationHelper.cs": {
                  "name": "MigrationHelper.cs",
                  "path": "EFCore.Sharding.git/src/EFCore.Sharding/Migrations/MigrationHelper.cs",
                  "isDir": false,
                  "isDockerfile": false,
                  "isComposefile": false
                },
                "ShardingMigration.cs": {
                  "name": "ShardingMigration.cs",
                  "path": "EFCore.Sharding.git/src/EFCore.Sharding/Migrations/ShardingMigration.cs",
                  "isDir": false,
                  "isDockerfile": false,
                  "isComposefile": false
                }
              }
            },
            "Options": {
              "name": "Options",
              "path": "EFCore.Sharding.git/src/EFCore.Sharding/Options",
              "isDir": true,
              "isDockerfile": false,
              "isComposefile": false,
              "children": {
                "EFCoreShardingOptions.cs": {
                  "name": "EFCoreShardingOptions.cs",
                  "path": "EFCore.Sharding.git/src/EFCore.Sharding/Options/EFCoreShardingOptions.cs",
                  "isDir": false,
                  "isDockerfile": false,
                  "isComposefile": false
                },
                "OptionExtentions.cs": {
                  "name": "OptionExtentions.cs",
                  "path": "EFCore.Sharding.git/src/EFCore.Sharding/Options/OptionExtentions.cs",
                  "isDir": false,
                  "isDockerfile": false,
                  "isComposefile": false
                }
              }
            },
            "Primitives": {
              "name": "Primitives",
              "path": "EFCore.Sharding.git/src/EFCore.Sharding/Primitives",
              "isDir": true,
              "isDockerfile": false,
              "isComposefile": false,
              "children": {
                "DataSource.cs": {
                  "name": "DataSource.cs",
                  "path": "EFCore.Sharding.git/src/EFCore.Sharding/Primitives/DataSource.cs",
                  "isDir": false,
                  "isDockerfile": false,
                  "isComposefile": false
                },
                "DatabaseType.cs": {
                  "name": "DatabaseType.cs",
                  "path": "EFCore.Sharding.git/src/EFCore.Sharding/Primitives/DatabaseType.cs",
                  "isDir": false,
                  "isDockerfile": false,
                  "isComposefile": false
                },
                "ExpandByDateMode.cs": {
                  "name": "ExpandByDateMode.cs",
                  "path": "EFCore.Sharding.git/src/EFCore.Sharding/Primitives/ExpandByDateMode.cs",
                  "isDir": false,
                  "isDockerfile": false,
                  "isComposefile": false
                },
                "PhysicTable.cs": {
                  "name": "PhysicTable.cs",
                  "path": "EFCore.Sharding.git/src/EFCore.Sharding/Primitives/PhysicTable.cs",
                  "isDir": false,
                  "isDockerfile": false,
                  "isComposefile": false
                },
                "ReadWriteType.cs": {
                  "name": "ReadWriteType.cs",
                  "path": "EFCore.Sharding.git/src/EFCore.Sharding/Primitives/ReadWriteType.cs",
                  "isDir": false,
                  "isDockerfile": false,
                  "isComposefile": false
                },
                "ShardingRule.cs": {
                  "name": "ShardingRule.cs",
                  "path": "EFCore.Sharding.git/src/EFCore.Sharding/Primitives/ShardingRule.cs",
                  "isDir": false,
                  "isDockerfile": false,
                  "isComposefile": false
                },
                "ShardingType.cs": {
                  "name": "ShardingType.cs",
                  "path": "EFCore.Sharding.git/src/EFCore.Sharding/Primitives/ShardingType.cs",
                  "isDir": false,
                  "isDockerfile": false,
                  "isComposefile": false
                },
                "UpdateType.cs": {
                  "name": "UpdateType.cs",
                  "path": "EFCore.Sharding.git/src/EFCore.Sharding/Primitives/UpdateType.cs",
                  "isDir": false,
                  "isDockerfile": false,
                  "isComposefile": false
                }
              }
            },
            "Sharding": {
              "name": "Sharding",
              "path": "EFCore.Sharding.git/src/EFCore.Sharding/Sharding",
              "isDir": true,
              "isDockerfile": false,
              "isComposefile": false,
              "children": {
                "IShardingQueryable.T.cs": {
                  "name": "IShardingQueryable.T.cs",
                  "path": "EFCore.Sharding.git/src/EFCore.Sharding/Sharding/IShardingQueryable.T.cs",
                  "isDir": false,
                  "isDockerfile": false,
                  "isComposefile": false
                },
                "ShardingDbAccessor.cs": {
                  "name": "ShardingDbAccessor.cs",
                  "path": "EFCore.Sharding.git/src/EFCore.Sharding/Sharding/ShardingDbAccessor.cs",
                  "isDir": false,
                  "isDockerfile": false,
                  "isComposefile": false
                },
                "ShardingHelper.cs": {
                  "name": "ShardingHelper.cs",
                  "path": "EFCore.Sharding.git/src/EFCore.Sharding/Sharding/ShardingHelper.cs",
                  "isDir": false,
                  "isDockerfile": false,
                  "isComposefile": false
                },
                "ShardingIQueryable.T.cs": {
                  "name": "ShardingIQueryable.T.cs",
                  "path": "EFCore.Sharding.git/src/EFCore.Sharding/Sharding/ShardingIQueryable.T.cs",
                  "isDir": false,
                  "isDockerfile": false,
                  "isComposefile": false
                }
              }
            },
            "Transaction": {
              "name": "Transaction",
              "path": "EFCore.Sharding.git/src/EFCore.Sharding/Transaction",
              "isDir": true,
              "isDockerfile": false,
              "isComposefile": false,
              "children": {
                "DistributedTransaction.cs": {
                  "name": "DistributedTransaction.cs",
                  "path": "EFCore.Sharding.git/src/EFCore.Sharding/Transaction/DistributedTransaction.cs",
                  "isDir": false,
                  "isDockerfile": false,
                  "isComposefile": false
                },
                "DistributedTransactionFactory.cs": {
                  "name": "DistributedTransactionFactory.cs",
                  "path": "EFCore.Sharding.git/src/EFCore.Sharding/Transaction/DistributedTransactionFactory.cs",
                  "isDir": false,
                  "isDockerfile": false,
                  "isComposefile": false
                },
                "IDistributedTransaction.cs": {
                  "name": "IDistributedTransaction.cs",
                  "path": "EFCore.Sharding.git/src/EFCore.Sharding/Transaction/IDistributedTransaction.cs",
                  "isDir": false,
                  "isDockerfile": false,
                  "isComposefile": false
                },
                "ITransaction.cs": {
                  "name": "ITransaction.cs",
                  "path": "EFCore.Sharding.git/src/EFCore.Sharding/Transaction/ITransaction.cs",
                  "isDir": false,
                  "isDockerfile": false,
                  "isComposefile": false
                }
              }
            },
            "Util": {
              "name": "Util",
              "path": "EFCore.Sharding.git/src/EFCore.Sharding/Util",
              "isDir": true,
              "isDockerfile": false,
              "isComposefile": false,
              "children": {
                "AnnotationHelper.cs": {
                  "name": "AnnotationHelper.cs",
                  "path": "EFCore.Sharding.git/src/EFCore.Sharding/Util/AnnotationHelper.cs",
                  "isDir": false,
                  "isDockerfile": false,
                  "isComposefile": false
                },
                "AsyncHelper.cs": {
                  "name": "AsyncHelper.cs",
                  "path": "EFCore.Sharding.git/src/EFCore.Sharding/Util/AsyncHelper.cs",
                  "isDir": false,
                  "isDockerfile": false,
                  "isComposefile": false
                },
                "DatabaseTypeExtentions.cs": {
                  "name": "DatabaseTypeExtentions.cs",
                  "path": "EFCore.Sharding.git/src/EFCore.Sharding/Util/DatabaseTypeExtentions.cs",
                  "isDir": false,
                  "isDockerfile": false,
                  "isComposefile": false
                },
                "DeepCloneExtensions.cs": {
                  "name": "DeepCloneExtensions.cs",
                  "path": "EFCore.Sharding.git/src/EFCore.Sharding/Util/DeepCloneExtensions.cs",
                  "isDir": false,
                  "isDockerfile": false,
                  "isComposefile": false
                },
                "Extension.Type.cs": {
                  "name": "Extension.Type.cs",
                  "path": "EFCore.Sharding.git/src/EFCore.Sharding/Util/Extension.Type.cs",
                  "isDir": false,
                  "isDockerfile": false,
                  "isComposefile": false
                },
                "Extention.DataTable.cs": {
                  "name": "Extention.DataTable.cs",
                  "path": "EFCore.Sharding.git/src/EFCore.Sharding/Util/Extention.DataTable.cs",
                  "isDir": false,
                  "isDockerfile": false,
                  "isComposefile": false
                },
                "Extention.Expression.cs": {
                  "name": "Extention.Expression.cs",
                  "path": "EFCore.Sharding.git/src/EFCore.Sharding/Util/Extention.Expression.cs",
                  "isDir": false,
                  "isDockerfile": false,
                  "isComposefile": false
                },
                "Extention.IEnumerable.cs": {
                  "name": "Extention.IEnumerable.cs",
                  "path": "EFCore.Sharding.git/src/EFCore.Sharding/Util/Extention.IEnumerable.cs",
                  "isDir": false,
                  "isDockerfile": false,
                  "isComposefile": false
                },
                "Extention.IQueryable.cs": {
                  "name": "Extention.IQueryable.cs",
                  "path": "EFCore.Sharding.git/src/EFCore.Sharding/Util/Extention.IQueryable.cs",
                  "isDir": false,
                  "isDockerfile": false,
                  "isComposefile": false
                },
                "Extention.Object.cs": {
                  "name": "Extention.Object.cs",
                  "path": "EFCore.Sharding.git/src/EFCore.Sharding/Util/Extention.Object.cs",
                  "isDir": false,
                  "isDockerfile": false,
                  "isComposefile": false
                },
                "Extention.String.cs": {
                  "name": "Extention.String.cs",
                  "path": "EFCore.Sharding.git/src/EFCore.Sharding/Util/Extention.String.cs",
                  "isDir": false,
                  "isDockerfile": false,
                  "isComposefile": false
                },
                "JobHelper.cs": {
                  "name": "JobHelper.cs",
                  "path": "EFCore.Sharding.git/src/EFCore.Sharding/Util/JobHelper.cs",
                  "isDir": false,
                  "isDockerfile": false,
                  "isComposefile": false
                },
                "RandomHelper.cs": {
                  "name": "RandomHelper.cs",
                  "path": "EFCore.Sharding.git/src/EFCore.Sharding/Util/RandomHelper.cs",
                  "isDir": false,
                  "isDockerfile": false,
                  "isComposefile": false
                }
              }
            }
          }
        },
        "EFCore.Sharding.MySql": {
          "name": "EFCore.Sharding.MySql",
          "path": "EFCore.Sharding.git/src/EFCore.Sharding.MySql",
          "isDir": true,
          "isDockerfile": false,
          "isComposefile": false,
          "children": {
            "EFCore.Sharding.MySql.csproj": {
              "name": "EFCore.Sharding.MySql.csproj",
              "path": "EFCore.Sharding.git/src/EFCore.Sharding.MySql/EFCore.Sharding.MySql.csproj",
              "isDir": false,
              "isDockerfile": false,
              "isComposefile": false
            },
            "MySqlDbAccessor.cs": {
              "name": "MySqlDbAccessor.cs",
              "path": "EFCore.Sharding.git/src/EFCore.Sharding.MySql/MySqlDbAccessor.cs",
              "isDir": false,
              "isDockerfile": false,
              "isComposefile": false
            },
            "MySqlProvider.cs": {
              "name": "MySqlProvider.cs",
              "path": "EFCore.Sharding.git/src/EFCore.Sharding.MySql/MySqlProvider.cs",
              "isDir": false,
              "isDockerfile": false,
              "isComposefile": false
            },
            "ShardingMySqlMigrationsSqlGenerator.cs": {
              "name": "ShardingMySqlMigrationsSqlGenerator.cs",
              "path": "EFCore.Sharding.git/src/EFCore.Sharding.MySql/ShardingMySqlMigrationsSqlGenerator.cs",
              "isDir": false,
              "isDockerfile": false,
              "isComposefile": false
            }
          }
        },
        "EFCore.Sharding.Oracle": {
          "name": "EFCore.Sharding.Oracle",
          "path": "EFCore.Sharding.git/src/EFCore.Sharding.Oracle",
          "isDir": true,
          "isDockerfile": false,
          "isComposefile": false,
          "children": {
            "EFCore.Sharding.Oracle.csproj": {
              "name": "EFCore.Sharding.Oracle.csproj",
              "path": "EFCore.Sharding.git/src/EFCore.Sharding.Oracle/EFCore.Sharding.Oracle.csproj",
              "isDir": false,
              "isDockerfile": false,
              "isComposefile": false
            },
            "OracleDbAccessor.cs": {
              "name": "OracleDbAccessor.cs",
              "path": "EFCore.Sharding.git/src/EFCore.Sharding.Oracle/OracleDbAccessor.cs",
              "isDir": false,
              "isDockerfile": false,
              "isComposefile": false
            },
            "OracleProvider.cs": {
              "name": "OracleProvider.cs",
              "path": "EFCore.Sharding.git/src/EFCore.Sharding.Oracle/OracleProvider.cs",
              "isDir": false,
              "isDockerfile": false,
              "isComposefile": false
            },
            "ShardingOracleMigrationsSqlGenerator.cs": {
              "name": "ShardingOracleMigrationsSqlGenerator.cs",
              "path": "EFCore.Sharding.git/src/EFCore.Sharding.Oracle/ShardingOracleMigrationsSqlGenerator.cs",
              "isDir": false,
              "isDockerfile": false,
              "isComposefile": false
            }
          }
        },
        "EFCore.Sharding.PostgreSql": {
          "name": "EFCore.Sharding.PostgreSql",
          "path": "EFCore.Sharding.git/src/EFCore.Sharding.PostgreSql",
          "isDir": true,
          "isDockerfile": false,
          "isComposefile": false,
          "children": {
            "EFCore.Sharding.PostgreSql.csproj": {
              "name": "EFCore.Sharding.PostgreSql.csproj",
              "path": "EFCore.Sharding.git/src/EFCore.Sharding.PostgreSql/EFCore.Sharding.PostgreSql.csproj",
              "isDir": false,
              "isDockerfile": false,
              "isComposefile": false
            },
            "PostgreSqlDbAccessor.cs": {
              "name": "PostgreSqlDbAccessor.cs",
              "path": "EFCore.Sharding.git/src/EFCore.Sharding.PostgreSql/PostgreSqlDbAccessor.cs",
              "isDir": false,
              "isDockerfile": false,
              "isComposefile": false
            },
            "PostgreSqlProvider.cs": {
              "name": "PostgreSqlProvider.cs",
              "path": "EFCore.Sharding.git/src/EFCore.Sharding.PostgreSql/PostgreSqlProvider.cs",
              "isDir": false,
              "isDockerfile": false,
              "isComposefile": false
            },
            "ShardingPostgreSqlMigrationsSqlGenerator.cs": {
              "name": "ShardingPostgreSqlMigrationsSqlGenerator.cs",
              "path": "EFCore.Sharding.git/src/EFCore.Sharding.PostgreSql/ShardingPostgreSqlMigrationsSqlGenerator.cs",
              "isDir": false,
              "isDockerfile": false,
              "isComposefile": false
            }
          }
        },
        "EFCore.Sharding.SQLite": {
          "name": "EFCore.Sharding.SQLite",
          "path": "EFCore.Sharding.git/src/EFCore.Sharding.SQLite",
          "isDir": true,
          "isDockerfile": false,
          "isComposefile": false,
          "children": {
            "EFCore.Sharding.SQLite.csproj": {
              "name": "EFCore.Sharding.SQLite.csproj",
              "path": "EFCore.Sharding.git/src/EFCore.Sharding.SQLite/EFCore.Sharding.SQLite.csproj",
              "isDir": false,
              "isDockerfile": false,
              "isComposefile": false
            },
            "SQLiteDbAccessor.cs": {
              "name": "SQLiteDbAccessor.cs",
              "path": "EFCore.Sharding.git/src/EFCore.Sharding.SQLite/SQLiteDbAccessor.cs",
              "isDir": false,
              "isDockerfile": false,
              "isComposefile": false
            },
            "SQLiteProvider.cs": {
              "name": "SQLiteProvider.cs",
              "path": "EFCore.Sharding.git/src/EFCore.Sharding.SQLite/SQLiteProvider.cs",
              "isDir": false,
              "isDockerfile": false,
              "isComposefile": false
            },
            "ShardingSQLiteMigrationsSqlGenerator.cs": {
              "name": "ShardingSQLiteMigrationsSqlGenerator.cs",
              "path": "EFCore.Sharding.git/src/EFCore.Sharding.SQLite/ShardingSQLiteMigrationsSqlGenerator.cs",
              "isDir": false,
              "isDockerfile": false,
              "isComposefile": false
            }
          }
        },
        "EFCore.Sharding.SqlServer": {
          "name": "EFCore.Sharding.SqlServer",
          "path": "EFCore.Sharding.git/src/EFCore.Sharding.SqlServer",
          "isDir": true,
          "isDockerfile": false,
          "isComposefile": false,
          "children": {
            "EFCore.Sharding.SqlServer.csproj": {
              "name": "EFCore.Sharding.SqlServer.csproj",
              "path": "EFCore.Sharding.git/src/EFCore.Sharding.SqlServer/EFCore.Sharding.SqlServer.csproj",
              "isDir": false,
              "isDockerfile": false,
              "isComposefile": false
            },
            "ShardingSqlServerMigrationsSqlGenerator.cs": {
              "name": "ShardingSqlServerMigrationsSqlGenerator.cs",
              "path": "EFCore.Sharding.git/src/EFCore.Sharding.SqlServer/ShardingSqlServerMigrationsSqlGenerator.cs",
              "isDir": false,
              "isDockerfile": false,
              "isComposefile": false
            },
            "SqlServerDbAccessor.cs": {
              "name": "SqlServerDbAccessor.cs",
              "path": "EFCore.Sharding.git/src/EFCore.Sharding.SqlServer/SqlServerDbAccessor.cs",
              "isDir": false,
              "isDockerfile": false,
              "isComposefile": false
            },
            "SqlServerProvider.cs": {
              "name": "SqlServerProvider.cs",
              "path": "EFCore.Sharding.git/src/EFCore.Sharding.SqlServer/SqlServerProvider.cs",
              "isDir": false,
              "isDockerfile": false,
              "isComposefile": false
            }
          }
        },
        "EFCore.Sharding.Tests": {
          "name": "EFCore.Sharding.Tests",
          "path": "EFCore.Sharding.git/src/EFCore.Sharding.Tests",
          "isDir": true,
          "isDockerfile": false,
          "isComposefile": false,
          "children": {
            "BaseTest.cs": {
              "name": "BaseTest.cs",
              "path": "EFCore.Sharding.git/src/EFCore.Sharding.Tests/BaseTest.cs",
              "isDir": false,
              "isDockerfile": false,
              "isComposefile": false
            },
            "Base_UnitTest.cs": {
              "name": "Base_UnitTest.cs",
              "path": "EFCore.Sharding.git/src/EFCore.Sharding.Tests/Base_UnitTest.cs",
              "isDir": false,
              "isDockerfile": false,
              "isComposefile": false
            },
            "Config.cs": {
              "name": "Config.cs",
              "path": "EFCore.Sharding.git/src/EFCore.Sharding.Tests/Config.cs",
              "isDir": false,
              "isDockerfile": false,
              "isComposefile": false
            },
            "DbAccessor": {
              "name": "DbAccessor",
              "path": "EFCore.Sharding.git/src/EFCore.Sharding.Tests/DbAccessor",
              "isDir": true,
              "isDockerfile": false,
              "isComposefile": false,
              "children": {
                "CustomDbAccessorTest.cs": {
                  "name": "CustomDbAccessorTest.cs",
                  "path": "EFCore.Sharding.git/src/EFCore.Sharding.Tests/DbAccessor/CustomDbAccessorTest.cs",
                  "isDir": false,
                  "isDockerfile": false,
                  "isComposefile": false
                },
                "DbAccessorTest.cs": {
                  "name": "DbAccessorTest.cs",
                  "path": "EFCore.Sharding.git/src/EFCore.Sharding.Tests/DbAccessor/DbAccessorTest.cs",
                  "isDir": false,
                  "isDockerfile": false,
                  "isComposefile": false
                },
                "ICustomDbAccessor.cs": {
                  "name": "ICustomDbAccessor.cs",
                  "path": "EFCore.Sharding.git/src/EFCore.Sharding.Tests/DbAccessor/ICustomDbAccessor.cs",
                  "isDir": false,
                  "isDockerfile": false,
                  "isComposefile": false
                }
              }
            },
            "EFCore.Sharding.Tests.csproj": {
              "name": "EFCore.Sharding.Tests.csproj",
              "path": "EFCore.Sharding.git/src/EFCore.Sharding.Tests/EFCore.Sharding.Tests.csproj",
              "isDir": false,
              "isDockerfile": false,
              "isComposefile": false
            },
            "EntityTypeConfigurations": {
              "name": "EntityTypeConfigurations",
              "path": "EFCore.Sharding.git/src/EFCore.Sharding.Tests/EntityTypeConfigurations",
              "isDir": true,
              "isDockerfile": false,
              "isComposefile": false,
              "children": {
                "Base_UnitTestConfiguration.cs": {
                  "name": "Base_UnitTestConfiguration.cs",
                  "path": "EFCore.Sharding.git/src/EFCore.Sharding.Tests/EntityTypeConfigurations/Base_UnitTestConfiguration.cs",
                  "isDir": false,
                  "isDockerfile": false,
                  "isComposefile": false
                }
              }
            },
            "ISQLiteDb1.cs": {
              "name": "ISQLiteDb1.cs",
              "path": "EFCore.Sharding.git/src/EFCore.Sharding.Tests/ISQLiteDb1.cs",
              "isDir": false,
              "isDockerfile": false,
              "isComposefile": false
            },
            "ISQLiteDb2.cs": {
              "name": "ISQLiteDb2.cs",
              "path": "EFCore.Sharding.git/src/EFCore.Sharding.Tests/ISQLiteDb2.cs",
              "isDir": false,
              "isDockerfile": false,
              "isComposefile": false
            },
            "Sharding": {
              "name": "Sharding",
              "path": "EFCore.Sharding.git/src/EFCore.Sharding.Tests/Sharding",
              "isDir": true,
              "isDockerfile": false,
              "isComposefile": false,
              "children": {
                "ShardingDbAccessorTest.cs": {
                  "name": "ShardingDbAccessorTest.cs",
                  "path": "EFCore.Sharding.git/src/EFCore.Sharding.Tests/Sharding/ShardingDbAccessorTest.cs",
                  "isDir": false,
                  "isDockerfile": false,
                  "isComposefile": false
                },
                "ShardingHelperTest.cs": {
                  "name": "ShardingHelperTest.cs",
                  "path": "EFCore.Sharding.git/src/EFCore.Sharding.Tests/Sharding/ShardingHelperTest.cs",
                  "isDir": false,
                  "isDockerfile": false,
                  "isComposefile": false
                },
                "ShardingIQueryableTest.cs": {
                  "name": "ShardingIQueryableTest.cs",
                  "path": "EFCore.Sharding.git/src/EFCore.Sharding.Tests/Sharding/ShardingIQueryableTest.cs",
                  "isDir": false,
                  "isDockerfile": false,
                  "isComposefile": false
                }
              }
            },
            "Startup.cs": {
              "name": "Startup.cs",
              "path": "EFCore.Sharding.git/src/EFCore.Sharding.Tests/Startup.cs",
              "isDir": false,
              "isDockerfile": false,
              "isComposefile": false
            },
            "Util": {
              "name": "Util",
              "path": "EFCore.Sharding.git/src/EFCore.Sharding.Tests/Util",
              "isDir": true,
              "isDockerfile": false,
              "isComposefile": false,
              "children": {
                "DeepCloneExtensions.cs": {
                  "name": "DeepCloneExtensions.cs",
                  "path": "EFCore.Sharding.git/src/EFCore.Sharding.Tests/Util/DeepCloneExtensions.cs",
                  "isDir": false,
                  "isDockerfile": false,
                  "isComposefile": false
                },
                "Extention.DataTable.cs": {
                  "name": "Extention.DataTable.cs",
                  "path": "EFCore.Sharding.git/src/EFCore.Sharding.Tests/Util/Extention.DataTable.cs",
                  "isDir": false,
                  "isDockerfile": false,
                  "isComposefile": false
                },
                "Extention.IEnumerable.cs": {
                  "name": "Extention.IEnumerable.cs",
                  "path": "EFCore.Sharding.git/src/EFCore.Sharding.Tests/Util/Extention.IEnumerable.cs",
                  "isDir": false,
                  "isDockerfile": false,
                  "isComposefile": false
                },
                "Extention.Object.cs": {
                  "name": "Extention.Object.cs",
                  "path": "EFCore.Sharding.git/src/EFCore.Sharding.Tests/Util/Extention.Object.cs",
                  "isDir": false,
                  "isDockerfile": false,
                  "isComposefile": false
                },
                "Extention.String.cs": {
                  "name": "Extention.String.cs",
                  "path": "EFCore.Sharding.git/src/EFCore.Sharding.Tests/Util/Extention.String.cs",
                  "isDir": false,
                  "isDockerfile": false,
                  "isComposefile": false
                }
              }
            },
            "db1.db": {
              "name": "db1.db",
              "path": "EFCore.Sharding.git/src/EFCore.Sharding.Tests/db1.db",
              "isDir": false,
              "isDockerfile": false,
              "isComposefile": false
            },
            "db2.db": {
              "name": "db2.db",
              "path": "EFCore.Sharding.git/src/EFCore.Sharding.Tests/db2.db",
              "isDir": false,
              "isDockerfile": false,
              "isComposefile": false
            }
          }
        }
      }
    }
  },
  "info": {
    "id": 234742043,
    "name": "EFCore.Sharding",
    "full_name": "Coldairarrow/EFCore.Sharding",
    "owner": {
      "login": "Coldairarrow",
      "html_url": "https://github.com/Coldairarrow",
      "type": "User"
    },
    "html_url": "https://github.com/Coldairarrow/EFCore.Sharding",
    "description": "Database Sharding For EFCore",
    "url": "https://api.github.com/repos/Coldairarrow/EFCore.Sharding",
    "clone_url": "https://github.com/Coldairarrow/EFCore.Sharding.git",
    "homepage": null,
    "size": 611,
    "stargazers_count": 658,
    "watchers_count": 658,
    "language": "C#"
  }
}