{
  "results": {
    "dockerfile": {
      "exist": false,
      "count": 0,
      "rootCount": 0,
      "subFolderCount": 0,
      "filepaths": []
    },
    "composefile": {
      "exist": false,
      "count": 0,
      "rootCount": 0,
      "subFolderCount": 0,
      "filepaths": []
    }
  },
  "struct": {
    ".babelrc": {
      "name": ".babelrc",
      "path": "react-aim.git/.babelrc",
      "isDir": false,
      "isDockerfile": false,
      "isComposefile": false
    },
    ".codeclimate.yml": {
      "name": ".codeclimate.yml",
      "path": "react-aim.git/.codeclimate.yml",
      "isDir": false,
      "isDockerfile": false,
      "isComposefile": false
    },
    ".editorconfig": {
      "name": ".editorconfig",
      "path": "react-aim.git/.editorconfig",
      "isDir": false,
      "isDockerfile": false,
      "isComposefile": false
    },
    ".eslintrc.yml": {
      "name": ".eslintrc.yml",
      "path": "react-aim.git/.eslintrc.yml",
      "isDir": false,
      "isDockerfile": false,
      "isComposefile": false
    },
    ".git": {
      "name": ".git",
      "path": "react-aim.git/.git",
      "isDir": true,
      "isDockerfile": false,
      "isComposefile": false,
      "children": {
        "HEAD": {
          "name": "HEAD",
          "path": "react-aim.git/.git/HEAD",
          "isDir": false,
          "isDockerfile": false,
          "isComposefile": false
        },
        "config": {
          "name": "config",
          "path": "react-aim.git/.git/config",
          "isDir": false,
          "isDockerfile": false,
          "isComposefile": false
        },
        "description": {
          "name": "description",
          "path": "react-aim.git/.git/description",
          "isDir": false,
          "isDockerfile": false,
          "isComposefile": false
        },
        "hooks": {
          "name": "hooks",
          "path": "react-aim.git/.git/hooks",
          "isDir": true,
          "isDockerfile": false,
          "isComposefile": false,
          "children": {
            "applypatch-msg.sample": {
              "name": "applypatch-msg.sample",
              "path": "react-aim.git/.git/hooks/applypatch-msg.sample",
              "isDir": false,
              "isDockerfile": false,
              "isComposefile": false
            },
            "commit-msg.sample": {
              "name": "commit-msg.sample",
              "path": "react-aim.git/.git/hooks/commit-msg.sample",
              "isDir": false,
              "isDockerfile": false,
              "isComposefile": false
            },
            "fsmonitor-watchman.sample": {
              "name": "fsmonitor-watchman.sample",
              "path": "react-aim.git/.git/hooks/fsmonitor-watchman.sample",
              "isDir": false,
              "isDockerfile": false,
              "isComposefile": false
            },
            "post-update.sample": {
              "name": "post-update.sample",
              "path": "react-aim.git/.git/hooks/post-update.sample",
              "isDir": false,
              "isDockerfile": false,
              "isComposefile": false
            },
            "pre-applypatch.sample": {
              "name": "pre-applypatch.sample",
              "path": "react-aim.git/.git/hooks/pre-applypatch.sample",
              "isDir": false,
              "isDockerfile": false,
              "isComposefile": false
            },
            "pre-commit.sample": {
              "name": "pre-commit.sample",
              "path": "react-aim.git/.git/hooks/pre-commit.sample",
              "isDir": false,
              "isDockerfile": false,
              "isComposefile": false
            },
            "pre-merge-commit.sample": {
              "name": "pre-merge-commit.sample",
              "path": "react-aim.git/.git/hooks/pre-merge-commit.sample",
              "isDir": false,
              "isDockerfile": false,
              "isComposefile": false
            },
            "pre-push.sample": {
              "name": "pre-push.sample",
              "path": "react-aim.git/.git/hooks/pre-push.sample",
              "isDir": false,
              "isDockerfile": false,
              "isComposefile": false
            },
            "pre-rebase.sample": {
              "name": "pre-rebase.sample",
              "path": "react-aim.git/.git/hooks/pre-rebase.sample",
              "isDir": false,
              "isDockerfile": false,
              "isComposefile": false
            },
            "pre-receive.sample": {
              "name": "pre-receive.sample",
              "path": "react-aim.git/.git/hooks/pre-receive.sample",
              "isDir": false,
              "isDockerfile": false,
              "isComposefile": false
            },
            "prepare-commit-msg.sample": {
              "name": "prepare-commit-msg.sample",
              "path": "react-aim.git/.git/hooks/prepare-commit-msg.sample",
              "isDir": false,
              "isDockerfile": false,
              "isComposefile": false
            },
            "push-to-checkout.sample": {
              "name": "push-to-checkout.sample",
              "path": "react-aim.git/.git/hooks/push-to-checkout.sample",
              "isDir": false,
              "isDockerfile": false,
              "isComposefile": false
            },
            "update.sample": {
              "name": "update.sample",
              "path": "react-aim.git/.git/hooks/update.sample",
              "isDir": false,
              "isDockerfile": false,
              "isComposefile": false
            }
          }
        },
        "index": {
          "name": "index",
          "path": "react-aim.git/.git/index",
          "isDir": false,
          "isDockerfile": false,
          "isComposefile": false
        },
        "info": {
          "name": "info",
          "path": "react-aim.git/.git/info",
          "isDir": true,
          "isDockerfile": false,
          "isComposefile": false,
          "children": {
            "exclude": {
              "name": "exclude",
              "path": "react-aim.git/.git/info/exclude",
              "isDir": false,
              "isDockerfile": false,
              "isComposefile": false
            }
          }
        },
        "logs": {
          "name": "logs",
          "path": "react-aim.git/.git/logs",
          "isDir": true,
          "isDockerfile": false,
          "isComposefile": false,
          "children": {
            "HEAD": {
              "name": "HEAD",
              "path": "react-aim.git/.git/logs/HEAD",
              "isDir": false,
              "isDockerfile": false,
              "isComposefile": false
            },
            "refs": {
              "name": "refs",
              "path": "react-aim.git/.git/logs/refs",
              "isDir": true,
              "isDockerfile": false,
              "isComposefile": false,
              "children": {
                "heads": {
                  "name": "heads",
                  "path": "react-aim.git/.git/logs/refs/heads",
                  "isDir": true,
                  "isDockerfile": false,
                  "isComposefile": false,
                  "children": {
                    "master": {
                      "name": "master",
                      "path": "react-aim.git/.git/logs/refs/heads/master",
                      "isDir": false,
                      "isDockerfile": false,
                      "isComposefile": false
                    }
                  }
                },
                "remotes": {
                  "name": "remotes",
                  "path": "react-aim.git/.git/logs/refs/remotes",
                  "isDir": true,
                  "isDockerfile": false,
                  "isComposefile": false,
                  "children": {
                    "origin": {
                      "name": "origin",
                      "path": "react-aim.git/.git/logs/refs/remotes/origin",
                      "isDir": true,
                      "isDockerfile": false,
                      "isComposefile": false,
                      "children": {
                        "HEAD": {
                          "name": "HEAD",
                          "path": "react-aim.git/.git/logs/refs/remotes/origin/HEAD",
                          "isDir": false,
                          "isDockerfile": false,
                          "isComposefile": false
                        }
                      }
                    }
                  }
                }
              }
            }
          }
        },
        "objects": {
          "name": "objects",
          "path": "react-aim.git/.git/objects",
          "isDir": true,
          "isDockerfile": false,
          "isComposefile": false,
          "children": {
            "info": {
              "name": "info",
              "path": "react-aim.git/.git/objects/info",
              "isDir": true,
              "isDockerfile": false,
              "isComposefile": false,
              "children": {}
            },
            "pack": {
              "name": "pack",
              "path": "react-aim.git/.git/objects/pack",
              "isDir": true,
              "isDockerfile": false,
              "isComposefile": false,
              "children": {
                "pack-eb09374df5fac8381bd679cbd71f68763bc5a1ea.idx": {
                  "name": "pack-eb09374df5fac8381bd679cbd71f68763bc5a1ea.idx",
                  "path": "react-aim.git/.git/objects/pack/pack-eb09374df5fac8381bd679cbd71f68763bc5a1ea.idx",
                  "isDir": false,
                  "isDockerfile": false,
                  "isComposefile": false
                },
                "pack-eb09374df5fac8381bd679cbd71f68763bc5a1ea.pack": {
                  "name": "pack-eb09374df5fac8381bd679cbd71f68763bc5a1ea.pack",
                  "path": "react-aim.git/.git/objects/pack/pack-eb09374df5fac8381bd679cbd71f68763bc5a1ea.pack",
                  "isDir": false,
                  "isDockerfile": false,
                  "isComposefile": false
                }
              }
            }
          }
        },
        "packed-refs": {
          "name": "packed-refs",
          "path": "react-aim.git/.git/packed-refs",
          "isDir": false,
          "isDockerfile": false,
          "isComposefile": false
        },
        "refs": {
          "name": "refs",
          "path": "react-aim.git/.git/refs",
          "isDir": true,
          "isDockerfile": false,
          "isComposefile": false,
          "children": {
            "heads": {
              "name": "heads",
              "path": "react-aim.git/.git/refs/heads",
              "isDir": true,
              "isDockerfile": false,
              "isComposefile": false,
              "children": {
                "master": {
                  "name": "master",
                  "path": "react-aim.git/.git/refs/heads/master",
                  "isDir": false,
                  "isDockerfile": false,
                  "isComposefile": false
                }
              }
            },
            "remotes": {
              "name": "remotes",
              "path": "react-aim.git/.git/refs/remotes",
              "isDir": true,
              "isDockerfile": false,
              "isComposefile": false,
              "children": {
                "origin": {
                  "name": "origin",
                  "path": "react-aim.git/.git/refs/remotes/origin",
                  "isDir": true,
                  "isDockerfile": false,
                  "isComposefile": false,
                  "children": {
                    "HEAD": {
                      "name": "HEAD",
                      "path": "react-aim.git/.git/refs/remotes/origin/HEAD",
                      "isDir": false,
                      "isDockerfile": false,
                      "isComposefile": false
                    }
                  }
                }
              }
            },
            "tags": {
              "name": "tags",
              "path": "react-aim.git/.git/refs/tags",
              "isDir": true,
              "isDockerfile": false,
              "isComposefile": false,
              "children": {}
            }
          }
        },
        "shallow": {
          "name": "shallow",
          "path": "react-aim.git/.git/shallow",
          "isDir": false,
          "isDockerfile": false,
          "isComposefile": false
        }
      }
    },
    ".gitignore": {
      "name": ".gitignore",
      "path": "react-aim.git/.gitignore",
      "isDir": false,
      "isDockerfile": false,
      "isComposefile": false
    },
    ".npmignore": {
      "name": ".npmignore",
      "path": "react-aim.git/.npmignore",
      "isDir": false,
      "isDockerfile": false,
      "isComposefile": false
    },
    ".travis.yml": {
      "name": ".travis.yml",
      "path": "react-aim.git/.travis.yml",
      "isDir": false,
      "isDockerfile": false,
      "isComposefile": false
    },
    "CHANGELOG.md": {
      "name": "CHANGELOG.md",
      "path": "react-aim.git/CHANGELOG.md",
      "isDir": false,
      "isDockerfile": false,
      "isComposefile": false
    },
    "LICENSE": {
      "name": "LICENSE",
      "path": "react-aim.git/LICENSE",
      "isDir": false,
      "isDockerfile": false,
      "isComposefile": false
    },
    "README.md": {
      "name": "README.md",
      "path": "react-aim.git/README.md",
      "isDir": false,
      "isDockerfile": false,
      "isComposefile": false
    },
    "example.gif": {
      "name": "example.gif",
      "path": "react-aim.git/example.gif",
      "isDir": false,
      "isDockerfile": false,
      "isComposefile": false
    },
    "examples": {
      "name": "examples",
      "path": "react-aim.git/examples",
      "isDir": true,
      "isDockerfile": false,
      "isComposefile": false,
      "children": {
        "menu": {
          "name": "menu",
          "path": "react-aim.git/examples/menu",
          "isDir": true,
          "isDockerfile": false,
          "isComposefile": false,
          "children": {
            "item.js": {
              "name": "item.js",
              "path": "react-aim.git/examples/menu/item.js",
              "isDir": false,
              "isDockerfile": false,
              "isComposefile": false
            },
            "menu.js": {
              "name": "menu.js",
              "path": "react-aim.git/examples/menu/menu.js",
              "isDir": false,
              "isDockerfile": false,
              "isComposefile": false
            },
            "submenu.js": {
              "name": "submenu.js",
              "path": "react-aim.git/examples/menu/submenu.js",
              "isDir": false,
              "isDockerfile": false,
              "isComposefile": false
            }
          }
        },
        "target": {
          "name": "target",
          "path": "react-aim.git/examples/target",
          "isDir": true,
          "isDockerfile": false,
          "isComposefile": false,
          "children": {
            "item.js": {
              "name": "item.js",
              "path": "react-aim.git/examples/target/item.js",
              "isDir": false,
              "isDockerfile": false,
              "isComposefile": false
            },
            "target.js": {
              "name": "target.js",
              "path": "react-aim.git/examples/target/target.js",
              "isDir": false,
              "isDockerfile": false,
              "isComposefile": false
            }
          }
        },
        "tooltip": {
          "name": "tooltip",
          "path": "react-aim.git/examples/tooltip",
          "isDir": true,
          "isDockerfile": false,
          "isComposefile": false,
          "children": {
            "source.js": {
              "name": "source.js",
              "path": "react-aim.git/examples/tooltip/source.js",
              "isDir": false,
              "isDockerfile": false,
              "isComposefile": false
            },
            "target.js": {
              "name": "target.js",
              "path": "react-aim.git/examples/tooltip/target.js",
              "isDir": false,
              "isDockerfile": false,
              "isComposefile": false
            },
            "tooltip.js": {
              "name": "tooltip.js",
              "path": "react-aim.git/examples/tooltip/tooltip.js",
              "isDir": false,
              "isDockerfile": false,
              "isComposefile": false
            }
          }
        },
        "zone": {
          "name": "zone",
          "path": "react-aim.git/examples/zone",
          "isDir": true,
          "isDockerfile": false,
          "isComposefile": false,
          "children": {
            "line.js": {
              "name": "line.js",
              "path": "react-aim.git/examples/zone/line.js",
              "isDir": false,
              "isDockerfile": false,
              "isComposefile": false
            },
            "rect.js": {
              "name": "rect.js",
              "path": "react-aim.git/examples/zone/rect.js",
              "isDir": false,
              "isDockerfile": false,
              "isComposefile": false
            },
            "zone.js": {
              "name": "zone.js",
              "path": "react-aim.git/examples/zone/zone.js",
              "isDir": false,
              "isDockerfile": false,
              "isComposefile": false
            }
          }
        }
      }
    },
    "index.d.ts": {
      "name": "index.d.ts",
      "path": "react-aim.git/index.d.ts",
      "isDir": false,
      "isDockerfile": false,
      "isComposefile": false
    },
    "package-lock.json": {
      "name": "package-lock.json",
      "path": "react-aim.git/package-lock.json",
      "isDir": false,
      "isDockerfile": false,
      "isComposefile": false
    },
    "package.json": {
      "name": "package.json",
      "path": "react-aim.git/package.json",
      "isDir": false,
      "isDockerfile": false,
      "isComposefile": false
    },
    "playground": {
      "name": "playground",
      "path": "react-aim.git/playground",
      "isDir": true,
      "isDockerfile": false,
      "isComposefile": false,
      "children": {
        "index.js": {
          "name": "index.js",
          "path": "react-aim.git/playground/index.js",
          "isDir": false,
          "isDockerfile": false,
          "isComposefile": false
        },
        "playground.js": {
          "name": "playground.js",
          "path": "react-aim.git/playground/playground.js",
          "isDir": false,
          "isDockerfile": false,
          "isComposefile": false
        },
        "webpack.config.js": {
          "name": "webpack.config.js",
          "path": "react-aim.git/playground/webpack.config.js",
          "isDir": false,
          "isDockerfile": false,
          "isComposefile": false
        }
      }
    },
    "src": {
      "name": "src",
      "path": "react-aim.git/src",
      "isDir": true,
      "isDockerfile": false,
      "isComposefile": false,
      "children": {
        "aim.js": {
          "name": "aim.js",
          "path": "react-aim.git/src/aim.js",
          "isDir": false,
          "isDockerfile": false,
          "isComposefile": false
        },
        "corners.js": {
          "name": "corners.js",
          "path": "react-aim.git/src/corners.js",
          "isDir": false,
          "isDockerfile": false,
          "isComposefile": false
        },
        "index.js": {
          "name": "index.js",
          "path": "react-aim.git/src/index.js",
          "isDir": false,
          "isDockerfile": false,
          "isComposefile": false
        },
        "monitor.js": {
          "name": "monitor.js",
          "path": "react-aim.git/src/monitor.js",
          "isDir": false,
          "isDockerfile": false,
          "isComposefile": false
        },
        "source.js": {
          "name": "source.js",
          "path": "react-aim.git/src/source.js",
          "isDir": false,
          "isDockerfile": false,
          "isComposefile": false
        },
        "target.js": {
          "name": "target.js",
          "path": "react-aim.git/src/target.js",
          "isDir": false,
          "isDockerfile": false,
          "isComposefile": false
        },
        "utils": {
          "name": "utils",
          "path": "react-aim.git/src/utils",
          "isDir": true,
          "isDockerfile": false,
          "isComposefile": false,
          "children": {
            "pointInPolygon.js": {
              "name": "pointInPolygon.js",
              "path": "react-aim.git/src/utils/pointInPolygon.js",
              "isDir": false,
              "isDockerfile": false,
              "isComposefile": false
            }
          }
        }
      }
    },
    "test": {
      "name": "test",
      "path": "react-aim.git/test",
      "isDir": true,
      "isDockerfile": false,
      "isComposefile": false,
      "children": {
        "mocha.opts": {
          "name": "mocha.opts",
          "path": "react-aim.git/test/mocha.opts",
          "isDir": false,
          "isDockerfile": false,
          "isComposefile": false
        },
        "setup.js": {
          "name": "setup.js",
          "path": "react-aim.git/test/setup.js",
          "isDir": false,
          "isDockerfile": false,
          "isComposefile": false
        },
        "tests": {
          "name": "tests",
          "path": "react-aim.git/test/tests",
          "isDir": true,
          "isDockerfile": false,
          "isComposefile": false,
          "children": {
            "index.js": {
              "name": "index.js",
              "path": "react-aim.git/test/tests/index.js",
              "isDir": false,
              "isDockerfile": false,
              "isComposefile": false
            }
          }
        }
      }
    }
  },
  "info": {
    "id": 60100466,
    "name": "react-aim",
    "full_name": "gabrielbull/react-aim",
    "owner": {
      "login": "gabrielbull",
      "html_url": "https://github.com/gabrielbull",
      "type": "User"
    },
    "html_url": "https://github.com/gabrielbull/react-aim",
    "description": "Determine the cursor aim for triggering mouse events.",
    "url": "https://api.github.com/repos/gabrielbull/react-aim",
    "clone_url": "https://github.com/gabrielbull/react-aim.git",
    "homepage": "http://gabrielbull.github.io/react-aim/",
    "size": 653,
    "stargazers_count": 366,
    "watchers_count": 366,
    "language": "JavaScript"
  }
}