{
  "results": {
    "dockerfile": {
      "exist": false,
      "count": 0,
      "rootCount": 0,
      "subFolderCount": 0,
      "filepaths": []
    },
    "composefile": {
      "exist": false,
      "count": 0,
      "rootCount": 0,
      "subFolderCount": 0,
      "filepaths": []
    }
  },
  "struct": {
    ".dir-locals.el": {
      "name": ".dir-locals.el",
      "path": "robe.git/.dir-locals.el",
      "isDir": false,
      "isDockerfile": false,
      "isComposefile": false
    },
    ".eproject": {
      "name": ".eproject",
      "path": "robe.git/.eproject",
      "isDir": false,
      "isDockerfile": false,
      "isComposefile": false
    },
    ".git": {
      "name": ".git",
      "path": "robe.git/.git",
      "isDir": true,
      "isDockerfile": false,
      "isComposefile": false,
      "children": {
        "HEAD": {
          "name": "HEAD",
          "path": "robe.git/.git/HEAD",
          "isDir": false,
          "isDockerfile": false,
          "isComposefile": false
        },
        "config": {
          "name": "config",
          "path": "robe.git/.git/config",
          "isDir": false,
          "isDockerfile": false,
          "isComposefile": false
        },
        "description": {
          "name": "description",
          "path": "robe.git/.git/description",
          "isDir": false,
          "isDockerfile": false,
          "isComposefile": false
        },
        "hooks": {
          "name": "hooks",
          "path": "robe.git/.git/hooks",
          "isDir": true,
          "isDockerfile": false,
          "isComposefile": false,
          "children": {
            "applypatch-msg.sample": {
              "name": "applypatch-msg.sample",
              "path": "robe.git/.git/hooks/applypatch-msg.sample",
              "isDir": false,
              "isDockerfile": false,
              "isComposefile": false
            },
            "commit-msg.sample": {
              "name": "commit-msg.sample",
              "path": "robe.git/.git/hooks/commit-msg.sample",
              "isDir": false,
              "isDockerfile": false,
              "isComposefile": false
            },
            "fsmonitor-watchman.sample": {
              "name": "fsmonitor-watchman.sample",
              "path": "robe.git/.git/hooks/fsmonitor-watchman.sample",
              "isDir": false,
              "isDockerfile": false,
              "isComposefile": false
            },
            "post-update.sample": {
              "name": "post-update.sample",
              "path": "robe.git/.git/hooks/post-update.sample",
              "isDir": false,
              "isDockerfile": false,
              "isComposefile": false
            },
            "pre-applypatch.sample": {
              "name": "pre-applypatch.sample",
              "path": "robe.git/.git/hooks/pre-applypatch.sample",
              "isDir": false,
              "isDockerfile": false,
              "isComposefile": false
            },
            "pre-commit.sample": {
              "name": "pre-commit.sample",
              "path": "robe.git/.git/hooks/pre-commit.sample",
              "isDir": false,
              "isDockerfile": false,
              "isComposefile": false
            },
            "pre-merge-commit.sample": {
              "name": "pre-merge-commit.sample",
              "path": "robe.git/.git/hooks/pre-merge-commit.sample",
              "isDir": false,
              "isDockerfile": false,
              "isComposefile": false
            },
            "pre-push.sample": {
              "name": "pre-push.sample",
              "path": "robe.git/.git/hooks/pre-push.sample",
              "isDir": false,
              "isDockerfile": false,
              "isComposefile": false
            },
            "pre-rebase.sample": {
              "name": "pre-rebase.sample",
              "path": "robe.git/.git/hooks/pre-rebase.sample",
              "isDir": false,
              "isDockerfile": false,
              "isComposefile": false
            },
            "pre-receive.sample": {
              "name": "pre-receive.sample",
              "path": "robe.git/.git/hooks/pre-receive.sample",
              "isDir": false,
              "isDockerfile": false,
              "isComposefile": false
            },
            "prepare-commit-msg.sample": {
              "name": "prepare-commit-msg.sample",
              "path": "robe.git/.git/hooks/prepare-commit-msg.sample",
              "isDir": false,
              "isDockerfile": false,
              "isComposefile": false
            },
            "push-to-checkout.sample": {
              "name": "push-to-checkout.sample",
              "path": "robe.git/.git/hooks/push-to-checkout.sample",
              "isDir": false,
              "isDockerfile": false,
              "isComposefile": false
            },
            "update.sample": {
              "name": "update.sample",
              "path": "robe.git/.git/hooks/update.sample",
              "isDir": false,
              "isDockerfile": false,
              "isComposefile": false
            }
          }
        },
        "index": {
          "name": "index",
          "path": "robe.git/.git/index",
          "isDir": false,
          "isDockerfile": false,
          "isComposefile": false
        },
        "info": {
          "name": "info",
          "path": "robe.git/.git/info",
          "isDir": true,
          "isDockerfile": false,
          "isComposefile": false,
          "children": {
            "exclude": {
              "name": "exclude",
              "path": "robe.git/.git/info/exclude",
              "isDir": false,
              "isDockerfile": false,
              "isComposefile": false
            }
          }
        },
        "logs": {
          "name": "logs",
          "path": "robe.git/.git/logs",
          "isDir": true,
          "isDockerfile": false,
          "isComposefile": false,
          "children": {
            "HEAD": {
              "name": "HEAD",
              "path": "robe.git/.git/logs/HEAD",
              "isDir": false,
              "isDockerfile": false,
              "isComposefile": false
            },
            "refs": {
              "name": "refs",
              "path": "robe.git/.git/logs/refs",
              "isDir": true,
              "isDockerfile": false,
              "isComposefile": false,
              "children": {
                "heads": {
                  "name": "heads",
                  "path": "robe.git/.git/logs/refs/heads",
                  "isDir": true,
                  "isDockerfile": false,
                  "isComposefile": false,
                  "children": {
                    "master": {
                      "name": "master",
                      "path": "robe.git/.git/logs/refs/heads/master",
                      "isDir": false,
                      "isDockerfile": false,
                      "isComposefile": false
                    }
                  }
                },
                "remotes": {
                  "name": "remotes",
                  "path": "robe.git/.git/logs/refs/remotes",
                  "isDir": true,
                  "isDockerfile": false,
                  "isComposefile": false,
                  "children": {
                    "origin": {
                      "name": "origin",
                      "path": "robe.git/.git/logs/refs/remotes/origin",
                      "isDir": true,
                      "isDockerfile": false,
                      "isComposefile": false,
                      "children": {
                        "HEAD": {
                          "name": "HEAD",
                          "path": "robe.git/.git/logs/refs/remotes/origin/HEAD",
                          "isDir": false,
                          "isDockerfile": false,
                          "isComposefile": false
                        }
                      }
                    }
                  }
                }
              }
            }
          }
        },
        "objects": {
          "name": "objects",
          "path": "robe.git/.git/objects",
          "isDir": true,
          "isDockerfile": false,
          "isComposefile": false,
          "children": {
            "info": {
              "name": "info",
              "path": "robe.git/.git/objects/info",
              "isDir": true,
              "isDockerfile": false,
              "isComposefile": false,
              "children": {}
            },
            "pack": {
              "name": "pack",
              "path": "robe.git/.git/objects/pack",
              "isDir": true,
              "isDockerfile": false,
              "isComposefile": false,
              "children": {
                "pack-dd46f96999b6a9a3c9b465b0809bca4ef466650c.idx": {
                  "name": "pack-dd46f96999b6a9a3c9b465b0809bca4ef466650c.idx",
                  "path": "robe.git/.git/objects/pack/pack-dd46f96999b6a9a3c9b465b0809bca4ef466650c.idx",
                  "isDir": false,
                  "isDockerfile": false,
                  "isComposefile": false
                },
                "pack-dd46f96999b6a9a3c9b465b0809bca4ef466650c.pack": {
                  "name": "pack-dd46f96999b6a9a3c9b465b0809bca4ef466650c.pack",
                  "path": "robe.git/.git/objects/pack/pack-dd46f96999b6a9a3c9b465b0809bca4ef466650c.pack",
                  "isDir": false,
                  "isDockerfile": false,
                  "isComposefile": false
                }
              }
            }
          }
        },
        "packed-refs": {
          "name": "packed-refs",
          "path": "robe.git/.git/packed-refs",
          "isDir": false,
          "isDockerfile": false,
          "isComposefile": false
        },
        "refs": {
          "name": "refs",
          "path": "robe.git/.git/refs",
          "isDir": true,
          "isDockerfile": false,
          "isComposefile": false,
          "children": {
            "heads": {
              "name": "heads",
              "path": "robe.git/.git/refs/heads",
              "isDir": true,
              "isDockerfile": false,
              "isComposefile": false,
              "children": {
                "master": {
                  "name": "master",
                  "path": "robe.git/.git/refs/heads/master",
                  "isDir": false,
                  "isDockerfile": false,
                  "isComposefile": false
                }
              }
            },
            "remotes": {
              "name": "remotes",
              "path": "robe.git/.git/refs/remotes",
              "isDir": true,
              "isDockerfile": false,
              "isComposefile": false,
              "children": {
                "origin": {
                  "name": "origin",
                  "path": "robe.git/.git/refs/remotes/origin",
                  "isDir": true,
                  "isDockerfile": false,
                  "isComposefile": false,
                  "children": {
                    "HEAD": {
                      "name": "HEAD",
                      "path": "robe.git/.git/refs/remotes/origin/HEAD",
                      "isDir": false,
                      "isDockerfile": false,
                      "isComposefile": false
                    }
                  }
                }
              }
            },
            "tags": {
              "name": "tags",
              "path": "robe.git/.git/refs/tags",
              "isDir": true,
              "isDockerfile": false,
              "isComposefile": false,
              "children": {}
            }
          }
        },
        "shallow": {
          "name": "shallow",
          "path": "robe.git/.git/shallow",
          "isDir": false,
          "isDockerfile": false,
          "isComposefile": false
        }
      }
    },
    ".gitignore": {
      "name": ".gitignore",
      "path": "robe.git/.gitignore",
      "isDir": false,
      "isDockerfile": false,
      "isComposefile": false
    },
    ".travis.yml": {
      "name": ".travis.yml",
      "path": "robe.git/.travis.yml",
      "isDir": false,
      "isDockerfile": false,
      "isComposefile": false
    },
    "Gemfile": {
      "name": "Gemfile",
      "path": "robe.git/Gemfile",
      "isDir": false,
      "isDockerfile": false,
      "isComposefile": false
    },
    "Gemfile.lock": {
      "name": "Gemfile.lock",
      "path": "robe.git/Gemfile.lock",
      "isDir": false,
      "isDockerfile": false,
      "isComposefile": false
    },
    "README.md": {
      "name": "README.md",
      "path": "robe.git/README.md",
      "isDir": false,
      "isDockerfile": false,
      "isComposefile": false
    },
    "Rakefile": {
      "name": "Rakefile",
      "path": "robe.git/Rakefile",
      "isDir": false,
      "isDockerfile": false,
      "isComposefile": false
    },
    "ac-robe.el": {
      "name": "ac-robe.el",
      "path": "robe.git/ac-robe.el",
      "isDir": false,
      "isDockerfile": false,
      "isComposefile": false
    },
    "build.el": {
      "name": "build.el",
      "path": "robe.git/build.el",
      "isDir": false,
      "isDockerfile": false,
      "isComposefile": false
    },
    "company-robe.el": {
      "name": "company-robe.el",
      "path": "robe.git/company-robe.el",
      "isDir": false,
      "isDockerfile": false,
      "isComposefile": false
    },
    "ert": {
      "name": "ert",
      "path": "robe.git/ert",
      "isDir": true,
      "isDockerfile": false,
      "isComposefile": false,
      "children": {
        "completion-tests.el": {
          "name": "completion-tests.el",
          "path": "robe.git/ert/completion-tests.el",
          "isDir": false,
          "isDockerfile": false,
          "isComposefile": false
        },
        "core-tests.el": {
          "name": "core-tests.el",
          "path": "robe.git/ert/core-tests.el",
          "isDir": false,
          "isDockerfile": false,
          "isComposefile": false
        }
      }
    },
    "lib": {
      "name": "lib",
      "path": "robe.git/lib",
      "isDir": true,
      "isDockerfile": false,
      "isComposefile": false,
      "children": {
        "robe": {
          "name": "robe",
          "path": "robe.git/lib/robe",
          "isDir": true,
          "isDockerfile": false,
          "isComposefile": false,
          "children": {
            "core_ext.rb": {
              "name": "core_ext.rb",
              "path": "robe.git/lib/robe/core_ext.rb",
              "isDir": false,
              "isDockerfile": false,
              "isComposefile": false
            },
            "jvisor.rb": {
              "name": "jvisor.rb",
              "path": "robe.git/lib/robe/jvisor.rb",
              "isDir": false,
              "isDockerfile": false,
              "isComposefile": false
            },
            "sash": {
              "name": "sash",
              "path": "robe.git/lib/robe/sash",
              "isDir": true,
              "isDockerfile": false,
              "isComposefile": false,
              "children": {
                "const_locations.rb": {
                  "name": "const_locations.rb",
                  "path": "robe.git/lib/robe/sash/const_locations.rb",
                  "isDir": false,
                  "isDockerfile": false,
                  "isComposefile": false
                },
                "doc_for.rb": {
                  "name": "doc_for.rb",
                  "path": "robe.git/lib/robe/sash/doc_for.rb",
                  "isDir": false,
                  "isDockerfile": false,
                  "isComposefile": false
                },
                "includes_tracker.rb": {
                  "name": "includes_tracker.rb",
                  "path": "robe.git/lib/robe/sash/includes_tracker.rb",
                  "isDir": false,
                  "isDockerfile": false,
                  "isComposefile": false
                }
              }
            },
            "sash.rb": {
              "name": "sash.rb",
              "path": "robe.git/lib/robe/sash.rb",
              "isDir": false,
              "isDockerfile": false,
              "isComposefile": false
            },
            "scanners.rb": {
              "name": "scanners.rb",
              "path": "robe.git/lib/robe/scanners.rb",
              "isDir": false,
              "isDockerfile": false,
              "isComposefile": false
            },
            "server.rb": {
              "name": "server.rb",
              "path": "robe.git/lib/robe/server.rb",
              "isDir": false,
              "isDockerfile": false,
              "isComposefile": false
            },
            "type_space.rb": {
              "name": "type_space.rb",
              "path": "robe.git/lib/robe/type_space.rb",
              "isDir": false,
              "isDockerfile": false,
              "isComposefile": false
            },
            "visor.rb": {
              "name": "visor.rb",
              "path": "robe.git/lib/robe/visor.rb",
              "isDir": false,
              "isDockerfile": false,
              "isComposefile": false
            }
          }
        },
        "robe.rb": {
          "name": "robe.rb",
          "path": "robe.git/lib/robe.rb",
          "isDir": false,
          "isDockerfile": false,
          "isComposefile": false
        }
      }
    },
    "robe.el": {
      "name": "robe.el",
      "path": "robe.git/robe.el",
      "isDir": false,
      "isDockerfile": false,
      "isComposefile": false
    },
    "screenshots": {
      "name": "screenshots",
      "path": "robe.git/screenshots",
      "isDir": true,
      "isDockerfile": false,
      "isComposefile": false,
      "children": {
        "company-robe.png": {
          "name": "company-robe.png",
          "path": "robe.git/screenshots/company-robe.png",
          "isDir": false,
          "isDockerfile": false,
          "isComposefile": false
        }
      }
    },
    "spec": {
      "name": "spec",
      "path": "robe.git/spec",
      "isDir": true,
      "isDockerfile": false,
      "isComposefile": false,
      "children": {
        "fixtures": {
          "name": "fixtures",
          "path": "robe.git/spec/fixtures",
          "isDir": true,
          "isDockerfile": false,
          "isComposefile": false,
          "children": {
            "sample_class.rb": {
              "name": "sample_class.rb",
              "path": "robe.git/spec/fixtures/sample_class.rb",
              "isDir": false,
              "isDockerfile": false,
              "isComposefile": false
            },
            "sample_methodless_class.rb": {
              "name": "sample_methodless_class.rb",
              "path": "robe.git/spec/fixtures/sample_methodless_class.rb",
              "isDir": false,
              "isDockerfile": false,
              "isComposefile": false
            },
            "sample_methodless_subclass.rb": {
              "name": "sample_methodless_subclass.rb",
              "path": "robe.git/spec/fixtures/sample_methodless_subclass.rb",
              "isDir": false,
              "isDockerfile": false,
              "isComposefile": false
            },
            "sample_module.rb": {
              "name": "sample_module.rb",
              "path": "robe.git/spec/fixtures/sample_module.rb",
              "isDir": false,
              "isDockerfile": false,
              "isComposefile": false
            },
            "sample_private_class.rb": {
              "name": "sample_private_class.rb",
              "path": "robe.git/spec/fixtures/sample_private_class.rb",
              "isDir": false,
              "isDockerfile": false,
              "isComposefile": false
            }
          }
        },
        "robe": {
          "name": "robe",
          "path": "robe.git/spec/robe",
          "isDir": true,
          "isDockerfile": false,
          "isComposefile": false,
          "children": {
            "jvisor_spec.rb": {
              "name": "jvisor_spec.rb",
              "path": "robe.git/spec/robe/jvisor_spec.rb",
              "isDir": false,
              "isDockerfile": false,
              "isComposefile": false
            },
            "method_scanner_spec.rb": {
              "name": "method_scanner_spec.rb",
              "path": "robe.git/spec/robe/method_scanner_spec.rb",
              "isDir": false,
              "isDockerfile": false,
              "isComposefile": false
            },
            "module_scanner_spec.rb": {
              "name": "module_scanner_spec.rb",
              "path": "robe.git/spec/robe/module_scanner_spec.rb",
              "isDir": false,
              "isDockerfile": false,
              "isComposefile": false
            },
            "sash": {
              "name": "sash",
              "path": "robe.git/spec/robe/sash",
              "isDir": true,
              "isDockerfile": false,
              "isComposefile": false,
              "children": {
                "const_locations_spec.rb": {
                  "name": "const_locations_spec.rb",
                  "path": "robe.git/spec/robe/sash/const_locations_spec.rb",
                  "isDir": false,
                  "isDockerfile": false,
                  "isComposefile": false
                },
                "doc_for_spec.rb": {
                  "name": "doc_for_spec.rb",
                  "path": "robe.git/spec/robe/sash/doc_for_spec.rb",
                  "isDir": false,
                  "isDockerfile": false,
                  "isComposefile": false
                },
                "includes_tracker_spec.rb": {
                  "name": "includes_tracker_spec.rb",
                  "path": "robe.git/spec/robe/sash/includes_tracker_spec.rb",
                  "isDir": false,
                  "isDockerfile": false,
                  "isComposefile": false
                }
              }
            },
            "sash_spec.rb": {
              "name": "sash_spec.rb",
              "path": "robe.git/spec/robe/sash_spec.rb",
              "isDir": false,
              "isDockerfile": false,
              "isComposefile": false
            },
            "server_spec.rb": {
              "name": "server_spec.rb",
              "path": "robe.git/spec/robe/server_spec.rb",
              "isDir": false,
              "isDockerfile": false,
              "isComposefile": false
            },
            "type_space_spec.rb": {
              "name": "type_space_spec.rb",
              "path": "robe.git/spec/robe/type_space_spec.rb",
              "isDir": false,
              "isDockerfile": false,
              "isComposefile": false
            },
            "visor_spec.rb": {
              "name": "visor_spec.rb",
              "path": "robe.git/spec/robe/visor_spec.rb",
              "isDir": false,
              "isDockerfile": false,
              "isComposefile": false
            }
          }
        },
        "robe_spec.rb": {
          "name": "robe_spec.rb",
          "path": "robe.git/spec/robe_spec.rb",
          "isDir": false,
          "isDockerfile": false,
          "isComposefile": false
        },
        "spec_helper.rb": {
          "name": "spec_helper.rb",
          "path": "robe.git/spec/spec_helper.rb",
          "isDir": false,
          "isDockerfile": false,
          "isComposefile": false
        },
        "support": {
          "name": "support",
          "path": "robe.git/spec/support",
          "isDir": true,
          "isDockerfile": false,
          "isComposefile": false,
          "children": {
            "mocks.rb": {
              "name": "mocks.rb",
              "path": "robe.git/spec/support/mocks.rb",
              "isDir": false,
              "isDockerfile": false,
              "isComposefile": false
            }
          }
        }
      }
    }
  },
  "info": {
    "id": 6716428,
    "name": "robe",
    "full_name": "dgutov/robe",
    "owner": {
      "login": "dgutov",
      "html_url": "https://github.com/dgutov",
      "type": "User"
    },
    "html_url": "https://github.com/dgutov/robe",
    "description": "Code navigation, documentation lookup and completion for Ruby",
    "url": "https://api.github.com/repos/dgutov/robe",
    "clone_url": "https://github.com/dgutov/robe.git",
    "homepage": "",
    "size": 576,
    "stargazers_count": 542,
    "watchers_count": 542,
    "language": "Emacs Lisp"
  }
}